[{"close":"0.05","high":"0.05","low":"0.05","open":"0.05","start_time":"2026-05-22T19:58:00Z","premium_mid_side":0,"premium_no_side":0,"premium_ask_side":5,"premium_bid_side":0,"volume_bid_side":0,"volume_ask_side":1,"volume_no_side":0,"volume_mid_side":0,"iv_low":"4.0287","iv_high":"4.0287","avg_price":"0.05","volume_multi":0,"volume_stock_multi":0},{"close":"0.03","high":"0.03","low":"0.03","open":"0.03","start_time":"2026-05-22T19:15:00Z","premium_mid_side":0,"premium_no_side":0,"premium_ask_side":3,"premium_bid_side":0,"volume_bid_side":0,"volume_ask_side":1,"volume_no_side":0,"volume_mid_side":0,"iv_low":"0.7157","iv_high":"0.7157","avg_price":"0.03","volume_multi":1,"volume_stock_multi":0},{"close":"0.05","high":"0.05","low":"0.05","open":"0.05","start_time":"2026-05-22T18:46:00Z","premium_mid_side":0,"premium_no_side":0,"premium_ask_side":5,"premium_bid_side":0,"volume_bid_side":0,"volume_ask_side":1,"volume_no_side":0,"volume_mid_side":0,"iv_low":"0.5540","iv_high":"0.5540","avg_price":"0.05","volume_multi":0,"volume_stock_multi":0},{"close":"0.03","high":"0.03","low":"0.02","open":"0.02","start_time":"2026-05-22T18:45:00Z","premium_mid_side":0,"premium_no_side":0,"premium_ask_side":24,"premium_bid_side":2,"volume_bid_side":1,"volume_ask_side":8,"volume_no_side":0,"volume_mid_side":0,"iv_low":"0.5017","iv_high":"0.5234","avg_price":"0.03","volume_multi":9,"volume_stock_multi":0},{"close":"0.05","high":"0.05","low":"0.05","open":"0.05","start_time":"2026-05-22T18:44:00Z","premium_mid_side":0,"premium_no_side":0,"premium_ask_side":50,"premium_bid_side":0,"volume_bid_side":0,"volume_ask_side":10,"volume_no_side":0,"volume_mid_side":0,"iv_low":"0.5404","iv_high":"0.5411","avg_price":"0.05","volume_multi":0,"volume_stock_multi":0},{"close":"0.05","high":"0.05","low":"0.03","open":"0.03","start_time":"2026-05-22T18:30:00Z","premium_mid_side":0,"premium_no_side":0,"premium_ask_side":68,"premium_bid_side":0,"volume_bid_side":0,"volume_ask_side":16,"volume_no_side":0,"volume_mid_side":0,"iv_low":"0.4778","iv_high":"0.5064","avg_price":"0.04","volume_multi":7,"volume_stock_multi":0},{"close":"0.05","high":"0.05","low":"0.03","open":"0.05","start_time":"2026-05-22T18:28:00Z","premium_mid_side":0,"premium_no_side":0,"premium_ask_side":124,"premium_bid_side":0,"volume_bid_side":0,"volume_ask_side":26,"volume_no_side":0,"volume_mid_side":0,"iv_low":"0.4684","iv_high":"0.4979","avg_price":"0.05","volume_multi":6,"volume_stock_multi":0},{"close":"0.05","high":"0.05","low":"0.03","open":"0.03","start_time":"2026-05-22T18:27:00Z","premium_mid_side":0,"premium_no_side":0,"premium_ask_side":227,"premium_bid_side":0,"volume_bid_side":0,"volume_ask_side":51,"volume_no_side":0,"volume_mid_side":0,"iv_low":"0.4682","iv_high":"0.4949","avg_price":"0.04","volume_multi":25,"volume_stock_multi":0},{"close":"0.05","high":"0.05","low":"0.03","open":"0.03","start_time":"2026-05-22T18:26:00Z","premium_mid_side":0,"premium_no_side":0,"premium_ask_side":105,"premium_bid_side":0,"volume_bid_side":0,"volume_ask_side":29,"volume_no_side":0,"volume_mid_side":0,"iv_low":"0.4635","iv_high":"0.4916","avg_price":"0.03","volume_multi":25,"volume_stock_multi":0},{"close":"0.05","high":"0.05","low":"0.03","open":"0.05","start_time":"2026-05-22T18:25:00Z","premium_mid_side":0,"premium_no_side":0,"premium_ask_side":137,"premium_bid_side":0,"volume_bid_side":0,"volume_ask_side":33,"volume_no_side":0,"volume_mid_side":0,"iv_low":"0.4565","iv_high":"0.4845","avg_price":"0.04","volume_multi":17,"volume_stock_multi":0},{"close":"0.05","high":"0.05","low":"0.05","open":"0.05","start_time":"2026-05-22T18:24:00Z","premium_mid_side":0,"premium_no_side":0,"premium_ask_side":50,"premium_bid_side":0,"volume_bid_side":0,"volume_ask_side":10,"volume_no_side":0,"volume_mid_side":0,"iv_low":"0.4794","iv_high":"0.4794","avg_price":"0.05","volume_multi":0,"volume_stock_multi":0},{"close":"0.07","high":"0.10","low":"0.03","open":"0.05","start_time":"2026-05-22T18:20:00Z","premium_mid_side":35,"premium_no_side":0,"premium_ask_side":219,"premium_bid_side":21,"volume_bid_side":3,"volume_ask_side":34,"volume_no_side":0,"volume_mid_side":7,"iv_low":"0.4512","iv_high":"0.5115","avg_price":"0.06","volume_multi":33,"volume_stock_multi":0},{"close":"0.05","high":"0.10","low":"0.05","open":"0.10","start_time":"2026-05-22T18:18:00Z","premium_mid_side":0,"premium_no_side":0,"premium_ask_side":40,"premium_bid_side":0,"volume_bid_side":0,"volume_ask_side":5,"volume_no_side":0,"volume_mid_side":0,"iv_low":"0.4700","iv_high":"0.5109","avg_price":"0.08","volume_multi":2,"volume_stock_multi":0},{"close":"0.05","high":"0.05","low":"0.03","open":"0.03","start_time":"2026-05-22T18:17:00Z","premium_mid_side":0,"premium_no_side":0,"premium_ask_side":71,"premium_bid_side":0,"volume_bid_side":0,"volume_ask_side":15,"volume_no_side":0,"volume_mid_side":0,"iv_low":"0.4536","iv_high":"0.4763","avg_price":"0.05","volume_multi":5,"volume_stock_multi":0},{"close":"0.07","high":"0.07","low":"0.07","open":"0.07","start_time":"2026-05-22T18:10:00Z","premium_mid_side":0,"premium_no_side":0,"premium_ask_side":0,"premium_bid_side":21,"volume_bid_side":3,"volume_ask_side":0,"volume_no_side":0,"volume_mid_side":0,"iv_low":"0.4674","iv_high":"0.4674","avg_price":"0.07","volume_multi":3,"volume_stock_multi":0},{"close":"0.07","high":"0.10","low":"0.05","open":"0.05","start_time":"2026-05-22T18:08:00Z","premium_mid_side":335,"premium_no_side":0,"premium_ask_side":115,"premium_bid_side":21,"volume_bid_side":3,"volume_ask_side":12,"volume_no_side":0,"volume_mid_side":67,"iv_low":"0.4454","iv_high":"0.4792","avg_price":"0.06","volume_multi":4,"volume_stock_multi":0},{"close":"0.05","high":"0.05","low":"0.03","open":"0.05","start_time":"2026-05-22T18:07:00Z","premium_mid_side":0,"premium_no_side":0,"premium_ask_side":177,"premium_bid_side":0,"volume_bid_side":0,"volume_ask_side":42,"volume_no_side":0,"volume_mid_side":0,"iv_low":"0.4228","iv_high":"0.4489","avg_price":"0.04","volume_multi":32,"volume_stock_multi":0},{"close":"0.05","high":"0.05","low":"0.03","open":"0.05","start_time":"2026-05-22T18:06:00Z","premium_mid_side":0,"premium_no_side":0,"premium_ask_side":142,"premium_bid_side":0,"volume_bid_side":0,"volume_ask_side":33,"volume_no_side":0,"volume_mid_side":0,"iv_low":"0.4274","iv_high":"0.4488","avg_price":"0.04","volume_multi":21,"volume_stock_multi":0},{"close":"0.05","high":"0.10","low":"0.03","open":"0.05","start_time":"2026-05-22T18:04:00Z","premium_mid_side":5,"premium_no_side":0,"premium_ask_side":647,"premium_bid_side":0,"volume_bid_side":0,"volume_ask_side":126,"volume_no_side":0,"volume_mid_side":1,"iv_low":"0.4125","iv_high":"0.4772","avg_price":"0.05","volume_multi":19,"volume_stock_multi":0},{"close":"0.05","high":"0.05","low":"0.05","open":"0.05","start_time":"2026-05-22T18:03:00Z","premium_mid_side":10,"premium_no_side":0,"premium_ask_side":0,"premium_bid_side":0,"volume_bid_side":0,"volume_ask_side":0,"volume_no_side":0,"volume_mid_side":2,"iv_low":"0.4303","iv_high":"0.4303","avg_price":"0.05","volume_multi":2,"volume_stock_multi":0},{"close":"0.05","high":"0.05","low":"0.05","open":"0.05","start_time":"2026-05-22T18:00:00Z","premium_mid_side":55,"premium_no_side":0,"premium_ask_side":0,"premium_bid_side":0,"volume_bid_side":0,"volume_ask_side":0,"volume_no_side":0,"volume_mid_side":11,"iv_low":"0.4298","iv_high":"0.4317","avg_price":"0.05","volume_multi":11,"volume_stock_multi":0},{"close":"0.03","high":"0.03","low":"0.03","open":"0.03","start_time":"2026-05-22T17:57:00Z","premium_mid_side":0,"premium_no_side":0,"premium_ask_side":3,"premium_bid_side":0,"volume_bid_side":0,"volume_ask_side":1,"volume_no_side":0,"volume_mid_side":0,"iv_low":"0.4034","iv_high":"0.4034","avg_price":"0.03","volume_multi":1,"volume_stock_multi":0},{"close":"0.05","high":"0.05","low":"0.05","open":"0.05","start_time":"2026-05-22T17:54:00Z","premium_mid_side":0,"premium_no_side":0,"premium_ask_side":40,"premium_bid_side":0,"volume_bid_side":0,"volume_ask_side":8,"volume_no_side":0,"volume_mid_side":0,"iv_low":"0.4192","iv_high":"0.4192","avg_price":"0.05","volume_multi":0,"volume_stock_multi":0},{"close":"0.05","high":"0.05","low":"0.03","open":"0.03","start_time":"2026-05-22T17:51:00Z","premium_mid_side":90,"premium_no_side":0,"premium_ask_side":37,"premium_bid_side":25,"volume_bid_side":5,"volume_ask_side":11,"volume_no_side":0,"volume_mid_side":18,"iv_low":"0.3924","iv_high":"0.4144","avg_price":"0.04","volume_multi":15,"volume_stock_multi":0},{"close":"0.05","high":"0.05","low":"0.03","open":"0.05","start_time":"2026-05-22T17:50:00Z","premium_mid_side":20,"premium_no_side":0,"premium_ask_side":18,"premium_bid_side":0,"volume_bid_side":0,"volume_ask_side":4,"volume_no_side":0,"volume_mid_side":4,"iv_low":"0.3871","iv_high":"0.4129","avg_price":"0.05","volume_multi":5,"volume_stock_multi":0},{"close":"0.05","high":"0.05","low":"0.05","open":"0.05","start_time":"2026-05-22T17:47:00Z","premium_mid_side":15,"premium_no_side":0,"premium_ask_side":0,"premium_bid_side":0,"volume_bid_side":0,"volume_ask_side":0,"volume_no_side":0,"volume_mid_side":3,"iv_low":"0.3954","iv_high":"0.3963","avg_price":"0.05","volume_multi":3,"volume_stock_multi":0},{"close":"0.05","high":"0.05","low":"0.05","open":"0.05","start_time":"2026-05-22T17:45:00Z","premium_mid_side":10,"premium_no_side":0,"premium_ask_side":0,"premium_bid_side":0,"volume_bid_side":0,"volume_ask_side":0,"volume_no_side":0,"volume_mid_side":2,"iv_low":"0.3881","iv_high":"0.3913","avg_price":"0.05","volume_multi":2,"volume_stock_multi":0},{"close":"0.05","high":"0.05","low":"0.05","open":"0.05","start_time":"2026-05-22T17:44:00Z","premium_mid_side":10,"premium_no_side":0,"premium_ask_side":0,"premium_bid_side":0,"volume_bid_side":0,"volume_ask_side":0,"volume_no_side":0,"volume_mid_side":2,"iv_low":"0.3805","iv_high":"0.3813","avg_price":"0.05","volume_multi":2,"volume_stock_multi":0},{"close":"0.05","high":"0.05","low":"0.05","open":"0.05","start_time":"2026-05-22T17:42:00Z","premium_mid_side":10,"premium_no_side":0,"premium_ask_side":0,"premium_bid_side":0,"volume_bid_side":0,"volume_ask_side":0,"volume_no_side":0,"volume_mid_side":2,"iv_low":"0.3813","iv_high":"0.3813","avg_price":"0.05","volume_multi":2,"volume_stock_multi":0},{"close":"0.05","high":"0.10","low":"0.03","open":"0.05","start_time":"2026-05-22T17:40:00Z","premium_mid_side":35,"premium_no_side":0,"premium_ask_side":68,"premium_bid_side":0,"volume_bid_side":0,"volume_ask_side":8,"volume_no_side":0,"volume_mid_side":7,"iv_low":"0.3573","iv_high":"0.4068","avg_price":"0.07","volume_multi":9,"volume_stock_multi":0},{"close":"0.03","high":"0.03","low":"0.03","open":"0.03","start_time":"2026-05-22T17:39:00Z","premium_mid_side":0,"premium_no_side":0,"premium_ask_side":3,"premium_bid_side":0,"volume_bid_side":0,"volume_ask_side":1,"volume_no_side":0,"volume_mid_side":0,"iv_low":"0.3573","iv_high":"0.3573","avg_price":"0.03","volume_multi":1,"volume_stock_multi":0},{"close":"0.05","high":"0.05","low":"0.05","open":"0.05","start_time":"2026-05-22T17:35:00Z","premium_mid_side":25,"premium_no_side":0,"premium_ask_side":0,"premium_bid_side":0,"volume_bid_side":0,"volume_ask_side":0,"volume_no_side":0,"volume_mid_side":5,"iv_low":"0.3727","iv_high":"0.3735","avg_price":"0.05","volume_multi":5,"volume_stock_multi":0},{"close":"0.05","high":"0.05","low":"0.05","open":"0.05","start_time":"2026-05-22T17:34:00Z","premium_mid_side":10,"premium_no_side":0,"premium_ask_side":0,"premium_bid_side":0,"volume_bid_side":0,"volume_ask_side":0,"volume_no_side":0,"volume_mid_side":2,"iv_low":"0.3757","iv_high":"0.3757","avg_price":"0.05","volume_multi":0,"volume_stock_multi":0},{"close":"0.05","high":"0.05","low":"0.05","open":"0.05","start_time":"2026-05-22T17:33:00Z","premium_mid_side":20,"premium_no_side":0,"premium_ask_side":0,"premium_bid_side":0,"volume_bid_side":0,"volume_ask_side":0,"volume_no_side":0,"volume_mid_side":4,"iv_low":"0.3708","iv_high":"0.3736","avg_price":"0.05","volume_multi":4,"volume_stock_multi":0},{"close":"0.05","high":"0.07","low":"0.05","open":"0.07","start_time":"2026-05-22T17:32:00Z","premium_mid_side":5,"premium_no_side":0,"premium_ask_side":0,"premium_bid_side":7,"volume_bid_side":1,"volume_ask_side":0,"volume_no_side":0,"volume_mid_side":1,"iv_low":"0.3693","iv_high":"0.3713","avg_price":"0.06","volume_multi":2,"volume_stock_multi":0},{"close":"0.07","high":"0.10","low":"0.07","open":"0.10","start_time":"2026-05-22T17:31:00Z","premium_mid_side":0,"premium_no_side":0,"premium_ask_side":20,"premium_bid_side":7,"volume_bid_side":1,"volume_ask_side":2,"volume_no_side":0,"volume_mid_side":0,"iv_low":"0.3664","iv_high":"0.3839","avg_price":"0.09","volume_multi":3,"volume_stock_multi":0},{"close":"0.05","high":"0.10","low":"0.05","open":"0.10","start_time":"2026-05-22T17:30:00Z","premium_mid_side":0,"premium_no_side":0,"premium_ask_side":18,"premium_bid_side":156,"volume_bid_side":30,"volume_ask_side":2,"volume_no_side":0,"volume_mid_side":0,"iv_low":"0.3551","iv_high":"0.3834","avg_price":"0.06","volume_multi":5,"volume_stock_multi":0},{"close":"0.05","high":"0.12","low":"0.05","open":"0.12","start_time":"2026-05-22T17:29:00Z","premium_mid_side":0,"premium_no_side":0,"premium_ask_side":12,"premium_bid_side":67,"volume_bid_side":11,"volume_ask_side":1,"volume_no_side":0,"volume_mid_side":0,"iv_low":"0.3498","iv_high":"0.3860","avg_price":"0.07","volume_multi":7,"volume_stock_multi":0},{"close":"0.05","high":"0.10","low":"0.05","open":"0.07","start_time":"2026-05-22T17:28:00Z","premium_mid_side":0,"premium_no_side":0,"premium_ask_side":350,"premium_bid_side":22,"volume_bid_side":4,"volume_ask_side":35,"volume_no_side":0,"volume_mid_side":0,"iv_low":"0.3705","iv_high":"0.4008","avg_price":"0.10","volume_multi":13,"volume_stock_multi":0},{"close":"0.07","high":"0.07","low":"0.07","open":"0.07","start_time":"2026-05-22T17:24:00Z","premium_mid_side":0,"premium_no_side":0,"premium_ask_side":0,"premium_bid_side":70,"volume_bid_side":10,"volume_ask_side":0,"volume_no_side":0,"volume_mid_side":0,"iv_low":"0.3953","iv_high":"0.3953","avg_price":"0.07","volume_multi":10,"volume_stock_multi":0},{"close":"0.07","high":"0.07","low":"0.07","open":"0.07","start_time":"2026-05-22T17:23:00Z","premium_mid_side":0,"premium_no_side":0,"premium_ask_side":0,"premium_bid_side":7,"volume_bid_side":1,"volume_ask_side":0,"volume_no_side":0,"volume_mid_side":0,"iv_low":"0.3911","iv_high":"0.3911","avg_price":"0.07","volume_multi":1,"volume_stock_multi":0},{"close":"0.05","high":"0.05","low":"0.05","open":"0.05","start_time":"2026-05-22T17:21:00Z","premium_mid_side":0,"premium_no_side":0,"premium_ask_side":0,"premium_bid_side":50,"volume_bid_side":10,"volume_ask_side":0,"volume_no_side":0,"volume_mid_side":0,"iv_low":"0.3767","iv_high":"0.3767","avg_price":"0.05","volume_multi":0,"volume_stock_multi":0},{"close":"0.10","high":"0.10","low":"0.10","open":"0.10","start_time":"2026-05-22T17:20:00Z","premium_mid_side":0,"premium_no_side":0,"premium_ask_side":150,"premium_bid_side":0,"volume_bid_side":0,"volume_ask_side":15,"volume_no_side":0,"volume_mid_side":0,"iv_low":"0.4067","iv_high":"0.4072","avg_price":"0.10","volume_multi":0,"volume_stock_multi":0},{"close":"0.08","high":"0.08","low":"0.08","open":"0.08","start_time":"2026-05-22T17:16:00Z","premium_mid_side":0,"premium_no_side":0,"premium_ask_side":24,"premium_bid_side":0,"volume_bid_side":0,"volume_ask_side":3,"volume_no_side":0,"volume_mid_side":0,"iv_low":"0.3782","iv_high":"0.3782","avg_price":"0.08","volume_multi":3,"volume_stock_multi":0},{"close":"0.10","high":"0.10","low":"0.10","open":"0.10","start_time":"2026-05-22T17:15:00Z","premium_mid_side":0,"premium_no_side":0,"premium_ask_side":20,"premium_bid_side":0,"volume_bid_side":0,"volume_ask_side":2,"volume_no_side":0,"volume_mid_side":0,"iv_low":"0.3868","iv_high":"0.3868","avg_price":"0.10","volume_multi":2,"volume_stock_multi":0},{"close":"0.07","high":"0.10","low":"0.07","open":"0.10","start_time":"2026-05-22T17:14:00Z","premium_mid_side":0,"premium_no_side":0,"premium_ask_side":10,"premium_bid_side":35,"volume_bid_side":5,"volume_ask_side":1,"volume_no_side":0,"volume_mid_side":0,"iv_low":"0.3723","iv_high":"0.3871","avg_price":"0.08","volume_multi":6,"volume_stock_multi":0},{"close":"0.07","high":"0.10","low":"0.07","open":"0.10","start_time":"2026-05-22T17:13:00Z","premium_mid_side":0,"premium_no_side":0,"premium_ask_side":20,"premium_bid_side":84,"volume_bid_side":12,"volume_ask_side":2,"volume_no_side":0,"volume_mid_side":0,"iv_low":"0.3720","iv_high":"0.3865","avg_price":"0.08","volume_multi":14,"volume_stock_multi":0},{"close":"0.10","high":"0.10","low":"0.07","open":"0.07","start_time":"2026-05-22T17:12:00Z","premium_mid_side":0,"premium_no_side":0,"premium_ask_side":26,"premium_bid_side":21,"volume_bid_side":3,"volume_ask_side":3,"volume_no_side":0,"volume_mid_side":0,"iv_low":"0.3681","iv_high":"0.3851","avg_price":"0.08","volume_multi":6,"volume_stock_multi":0},{"close":"0.10","high":"0.10","low":"0.08","open":"0.10","start_time":"2026-05-22T17:11:00Z","premium_mid_side":0,"premium_no_side":0,"premium_ask_side":38,"premium_bid_side":0,"volume_bid_side":0,"volume_ask_side":4,"volume_no_side":0,"volume_mid_side":0,"iv_low":"0.3698","iv_high":"0.3820","avg_price":"0.10","volume_multi":4,"volume_stock_multi":0},{"close":"0.07","high":"0.10","low":"0.07","open":"0.10","start_time":"2026-05-22T17:10:00Z","premium_mid_side":0,"premium_no_side":0,"premium_ask_side":370,"premium_bid_side":56,"volume_bid_side":8,"volume_ask_side":37,"volume_no_side":0,"volume_mid_side":0,"iv_low":"0.3660","iv_high":"0.3813","avg_price":"0.10","volume_multi":45,"volume_stock_multi":0},{"close":"0.07","high":"0.10","low":"0.07","open":"0.10","start_time":"2026-05-22T17:09:00Z","premium_mid_side":0,"premium_no_side":0,"premium_ask_side":10,"premium_bid_side":7,"volume_bid_side":1,"volume_ask_side":1,"volume_no_side":0,"volume_mid_side":0,"iv_low":"0.3666","iv_high":"0.3813","avg_price":"0.09","volume_multi":2,"volume_stock_multi":0},{"close":"0.07","high":"0.10","low":"0.07","open":"0.10","start_time":"2026-05-22T17:06:00Z","premium_mid_side":0,"premium_no_side":0,"premium_ask_side":30,"premium_bid_side":42,"volume_bid_side":6,"volume_ask_side":3,"volume_no_side":0,"volume_mid_side":0,"iv_low":"0.3600","iv_high":"0.3737","avg_price":"0.08","volume_multi":6,"volume_stock_multi":0},{"close":"0.07","high":"0.10","low":"0.07","open":"0.07","start_time":"2026-05-22T17:05:00Z","premium_mid_side":0,"premium_no_side":0,"premium_ask_side":42,"premium_bid_side":56,"volume_bid_side":8,"volume_ask_side":5,"volume_no_side":0,"volume_mid_side":0,"iv_low":"0.3591","iv_high":"0.3747","avg_price":"0.08","volume_multi":12,"volume_stock_multi":0},{"close":"0.10","high":"0.10","low":"0.10","open":"0.10","start_time":"2026-05-22T17:01:00Z","premium_mid_side":0,"premium_no_side":0,"premium_ask_side":20,"premium_bid_side":0,"volume_bid_side":0,"volume_ask_side":2,"volume_no_side":0,"volume_mid_side":0,"iv_low":"0.3755","iv_high":"0.3755","avg_price":"0.10","volume_multi":0,"volume_stock_multi":0},{"close":"0.05","high":"0.05","low":"0.05","open":"0.05","start_time":"2026-05-22T16:55:00Z","premium_mid_side":0,"premium_no_side":0,"premium_ask_side":0,"premium_bid_side":50,"volume_bid_side":10,"volume_ask_side":0,"volume_no_side":0,"volume_mid_side":0,"iv_low":"0.3475","iv_high":"0.3475","avg_price":"0.05","volume_multi":0,"volume_stock_multi":0},{"close":"0.07","high":"0.07","low":"0.07","open":"0.07","start_time":"2026-05-22T16:48:00Z","premium_mid_side":0,"premium_no_side":0,"premium_ask_side":0,"premium_bid_side":7,"volume_bid_side":1,"volume_ask_side":0,"volume_no_side":0,"volume_mid_side":0,"iv_low":"0.3526","iv_high":"0.3526","avg_price":"0.07","volume_multi":1,"volume_stock_multi":0},{"close":"0.10","high":"0.10","low":"0.10","open":"0.10","start_time":"2026-05-22T16:46:00Z","premium_mid_side":0,"premium_no_side":0,"premium_ask_side":100,"premium_bid_side":0,"volume_bid_side":0,"volume_ask_side":10,"volume_no_side":0,"volume_mid_side":0,"iv_low":"0.3632","iv_high":"0.3632","avg_price":"0.10","volume_multi":10,"volume_stock_multi":0},{"close":"0.05","high":"0.05","low":"0.05","open":"0.05","start_time":"2026-05-22T16:39:00Z","premium_mid_side":0,"premium_no_side":0,"premium_ask_side":0,"premium_bid_side":5,"volume_bid_side":1,"volume_ask_side":0,"volume_no_side":0,"volume_mid_side":0,"iv_low":"0.3429","iv_high":"0.3429","avg_price":"0.05","volume_multi":0,"volume_stock_multi":0},{"close":"0.10","high":"0.10","low":"0.05","open":"0.10","start_time":"2026-05-22T16:35:00Z","premium_mid_side":0,"premium_no_side":0,"premium_ask_side":70,"premium_bid_side":5,"volume_bid_side":1,"volume_ask_side":7,"volume_no_side":0,"volume_mid_side":0,"iv_low":"0.3376","iv_high":"0.3633","avg_price":"0.09","volume_multi":7,"volume_stock_multi":0},{"close":"0.10","high":"0.10","low":"0.07","open":"0.07","start_time":"2026-05-22T16:34:00Z","premium_mid_side":0,"premium_no_side":0,"premium_ask_side":10,"premium_bid_side":49,"volume_bid_side":7,"volume_ask_side":1,"volume_no_side":0,"volume_mid_side":0,"iv_low":"0.3455","iv_high":"0.3619","avg_price":"0.07","volume_multi":8,"volume_stock_multi":0},{"close":"0.10","high":"0.10","low":"0.05","open":"0.05","start_time":"2026-05-22T16:33:00Z","premium_mid_side":0,"premium_no_side":0,"premium_ask_side":40,"premium_bid_side":12,"volume_bid_side":2,"volume_ask_side":4,"volume_no_side":0,"volume_mid_side":0,"iv_low":"0.3255","iv_high":"0.3553","avg_price":"0.09","volume_multi":5,"volume_stock_multi":0},{"close":"0.10","high":"0.10","low":"0.07","open":"0.10","start_time":"2026-05-22T16:32:00Z","premium_mid_side":0,"premium_no_side":0,"premium_ask_side":80,"premium_bid_side":7,"volume_bid_side":1,"volume_ask_side":8,"volume_no_side":0,"volume_mid_side":0,"iv_low":"0.3346","iv_high":"0.3506","avg_price":"0.10","volume_multi":9,"volume_stock_multi":0},{"close":"0.10","high":"0.10","low":"0.07","open":"0.10","start_time":"2026-05-22T16:31:00Z","premium_mid_side":0,"premium_no_side":0,"premium_ask_side":176,"premium_bid_side":7,"volume_bid_side":1,"volume_ask_side":21,"volume_no_side":0,"volume_mid_side":0,"iv_low":"0.3360","iv_high":"0.3483","avg_price":"0.08","volume_multi":22,"volume_stock_multi":0},{"close":"0.08","high":"0.10","low":"0.07","open":"0.10","start_time":"2026-05-22T16:30:00Z","premium_mid_side":0,"premium_no_side":0,"premium_ask_side":144,"premium_bid_side":21,"volume_bid_side":3,"volume_ask_side":15,"volume_no_side":0,"volume_mid_side":0,"iv_low":"0.3373","iv_high":"0.3521","avg_price":"0.09","volume_multi":17,"volume_stock_multi":0},{"close":"0.10","high":"0.10","low":"0.07","open":"0.07","start_time":"2026-05-22T16:29:00Z","premium_mid_side":0,"premium_no_side":0,"premium_ask_side":156,"premium_bid_side":77,"volume_bid_side":11,"volume_ask_side":16,"volume_no_side":0,"volume_mid_side":0,"iv_low":"0.3388","iv_high":"0.3534","avg_price":"0.09","volume_multi":17,"volume_stock_multi":0},{"close":"0.10","high":"0.10","low":"0.07","open":"0.07","start_time":"2026-05-22T16:28:00Z","premium_mid_side":0,"premium_no_side":0,"premium_ask_side":160,"premium_bid_side":147,"volume_bid_side":21,"volume_ask_side":16,"volume_no_side":0,"volume_mid_side":0,"iv_low":"0.3386","iv_high":"0.3555","avg_price":"0.08","volume_multi":37,"volume_stock_multi":0},{"close":"0.10","high":"0.10","low":"0.07","open":"0.10","start_time":"2026-05-22T16:27:00Z","premium_mid_side":0,"premium_no_side":0,"premium_ask_side":188,"premium_bid_side":224,"volume_bid_side":32,"volume_ask_side":19,"volume_no_side":0,"volume_mid_side":0,"iv_low":"0.3378","iv_high":"0.3522","avg_price":"0.08","volume_multi":51,"volume_stock_multi":0},{"close":"0.07","high":"0.07","low":"0.07","open":"0.07","start_time":"2026-05-22T16:26:00Z","premium_mid_side":0,"premium_no_side":0,"premium_ask_side":0,"premium_bid_side":161,"volume_bid_side":23,"volume_ask_side":0,"volume_no_side":0,"volume_mid_side":0,"iv_low":"0.3394","iv_high":"0.3409","avg_price":"0.07","volume_multi":23,"volume_stock_multi":0},{"close":"0.09","high":"0.10","low":"0.07","open":"0.10","start_time":"2026-05-22T16:25:00Z","premium_mid_side":0,"premium_no_side":0,"premium_ask_side":280,"premium_bid_side":28,"volume_bid_side":4,"volume_ask_side":29,"volume_no_side":0,"volume_mid_side":0,"iv_low":"0.3412","iv_high":"0.3566","avg_price":"0.09","volume_multi":21,"volume_stock_multi":0},{"close":"0.08","high":"0.10","low":"0.07","open":"0.07","start_time":"2026-05-22T16:24:00Z","premium_mid_side":0,"premium_no_side":0,"premium_ask_side":162,"premium_bid_side":14,"volume_bid_side":2,"volume_ask_side":18,"volume_no_side":0,"volume_mid_side":0,"iv_low":"0.3391","iv_high":"0.3530","avg_price":"0.09","volume_multi":20,"volume_stock_multi":0},{"close":"0.10","high":"0.12","low":"0.10","open":"0.12","start_time":"2026-05-22T16:23:00Z","premium_mid_side":10,"premium_no_side":0,"premium_ask_side":0,"premium_bid_side":54,"volume_bid_side":5,"volume_ask_side":0,"volume_no_side":0,"volume_mid_side":1,"iv_low":"0.3495","iv_high":"0.3549","avg_price":"0.11","volume_multi":2,"volume_stock_multi":0},{"close":"0.10","high":"0.10","low":"0.10","open":"0.10","start_time":"2026-05-22T16:20:00Z","premium_mid_side":0,"premium_no_side":0,"premium_ask_side":0,"premium_bid_side":10,"volume_bid_side":1,"volume_ask_side":0,"volume_no_side":0,"volume_mid_side":0,"iv_low":"0.3509","iv_high":"0.3509","avg_price":"0.10","volume_multi":0,"volume_stock_multi":0},{"close":"0.10","high":"0.10","low":"0.10","open":"0.10","start_time":"2026-05-22T16:19:00Z","premium_mid_side":0,"premium_no_side":0,"premium_ask_side":0,"premium_bid_side":10,"volume_bid_side":1,"volume_ask_side":0,"volume_no_side":0,"volume_mid_side":0,"iv_low":"0.3487","iv_high":"0.3487","avg_price":"0.10","volume_multi":1,"volume_stock_multi":0},{"close":"0.10","high":"0.12","low":"0.10","open":"0.12","start_time":"2026-05-22T16:18:00Z","premium_mid_side":0,"premium_no_side":0,"premium_ask_side":0,"premium_bid_side":32,"volume_bid_side":3,"volume_ask_side":0,"volume_no_side":0,"volume_mid_side":0,"iv_low":"0.3471","iv_high":"0.3533","avg_price":"0.11","volume_multi":1,"volume_stock_multi":0},{"close":"0.10","high":"0.10","low":"0.10","open":"0.10","start_time":"2026-05-22T16:17:00Z","premium_mid_side":0,"premium_no_side":0,"premium_ask_side":0,"premium_bid_side":20,"volume_bid_side":2,"volume_ask_side":0,"volume_no_side":0,"volume_mid_side":0,"iv_low":"0.3460","iv_high":"0.3470","avg_price":"0.10","volume_multi":2,"volume_stock_multi":0},{"close":"0.12","high":"0.12","low":"0.12","open":"0.12","start_time":"2026-05-22T16:16:00Z","premium_mid_side":0,"premium_no_side":0,"premium_ask_side":0,"premium_bid_side":36,"volume_bid_side":3,"volume_ask_side":0,"volume_no_side":0,"volume_mid_side":0,"iv_low":"0.3565","iv_high":"0.3565","avg_price":"0.12","volume_multi":3,"volume_stock_multi":0},{"close":"0.12","high":"0.12","low":"0.12","open":"0.12","start_time":"2026-05-22T16:07:00Z","premium_mid_side":0,"premium_no_side":0,"premium_ask_side":0,"premium_bid_side":12,"volume_bid_side":1,"volume_ask_side":0,"volume_no_side":0,"volume_mid_side":0,"iv_low":"0.3370","iv_high":"0.3370","avg_price":"0.12","volume_multi":1,"volume_stock_multi":0},{"close":"0.12","high":"0.12","low":"0.10","open":"0.10","start_time":"2026-05-22T16:04:00Z","premium_mid_side":0,"premium_no_side":0,"premium_ask_side":0,"premium_bid_side":32,"volume_bid_side":3,"volume_ask_side":0,"volume_no_side":0,"volume_mid_side":0,"iv_low":"0.3240","iv_high":"0.3312","avg_price":"0.11","volume_multi":1,"volume_stock_multi":0},{"close":"0.10","high":"0.10","low":"0.10","open":"0.10","start_time":"2026-05-22T16:03:00Z","premium_mid_side":0,"premium_no_side":0,"premium_ask_side":0,"premium_bid_side":10,"volume_bid_side":1,"volume_ask_side":0,"volume_no_side":0,"volume_mid_side":0,"iv_low":"0.3244","iv_high":"0.3244","avg_price":"0.10","volume_multi":0,"volume_stock_multi":0},{"close":"0.12","high":"0.12","low":"0.12","open":"0.12","start_time":"2026-05-22T15:57:00Z","premium_mid_side":0,"premium_no_side":0,"premium_ask_side":0,"premium_bid_side":36,"volume_bid_side":3,"volume_ask_side":0,"volume_no_side":0,"volume_mid_side":0,"iv_low":"0.3270","iv_high":"0.3270","avg_price":"0.12","volume_multi":3,"volume_stock_multi":0},{"close":"0.14","high":"0.14","low":"0.14","open":"0.14","start_time":"2026-05-22T15:55:00Z","premium_mid_side":0,"premium_no_side":0,"premium_ask_side":14,"premium_bid_side":0,"volume_bid_side":0,"volume_ask_side":1,"volume_no_side":0,"volume_mid_side":0,"iv_low":"0.3306","iv_high":"0.3306","avg_price":"0.14","volume_multi":1,"volume_stock_multi":0},{"close":"0.10","high":"0.10","low":"0.10","open":"0.10","start_time":"2026-05-22T15:52:00Z","premium_mid_side":0,"premium_no_side":0,"premium_ask_side":0,"premium_bid_side":20,"volume_bid_side":2,"volume_ask_side":0,"volume_no_side":0,"volume_mid_side":0,"iv_low":"0.3152","iv_high":"0.3152","avg_price":"0.10","volume_multi":0,"volume_stock_multi":0},{"close":"0.12","high":"0.12","low":"0.12","open":"0.12","start_time":"2026-05-22T15:49:00Z","premium_mid_side":0,"premium_no_side":0,"premium_ask_side":0,"premium_bid_side":12,"volume_bid_side":1,"volume_ask_side":0,"volume_no_side":0,"volume_mid_side":0,"iv_low":"0.3283","iv_high":"0.3283","avg_price":"0.12","volume_multi":1,"volume_stock_multi":0},{"close":"0.12","high":"0.12","low":"0.12","open":"0.12","start_time":"2026-05-22T15:48:00Z","premium_mid_side":0,"premium_no_side":0,"premium_ask_side":0,"premium_bid_side":240,"volume_bid_side":20,"volume_ask_side":0,"volume_no_side":0,"volume_mid_side":0,"iv_low":"0.3238","iv_high":"0.3238","avg_price":"0.12","volume_multi":20,"volume_stock_multi":0},{"close":"0.12","high":"0.12","low":"0.12","open":"0.12","start_time":"2026-05-22T15:47:00Z","premium_mid_side":0,"premium_no_side":0,"premium_ask_side":0,"premium_bid_side":12,"volume_bid_side":1,"volume_ask_side":0,"volume_no_side":0,"volume_mid_side":0,"iv_low":"0.3199","iv_high":"0.3199","avg_price":"0.12","volume_multi":1,"volume_stock_multi":0},{"close":"0.12","high":"0.12","low":"0.12","open":"0.12","start_time":"2026-05-22T15:46:00Z","premium_mid_side":0,"premium_no_side":0,"premium_ask_side":0,"premium_bid_side":60,"volume_bid_side":5,"volume_ask_side":0,"volume_no_side":0,"volume_mid_side":0,"iv_low":"0.3182","iv_high":"0.3204","avg_price":"0.12","volume_multi":5,"volume_stock_multi":0},{"close":"0.12","high":"0.12","low":"0.12","open":"0.12","start_time":"2026-05-22T15:45:00Z","premium_mid_side":0,"premium_no_side":0,"premium_ask_side":0,"premium_bid_side":12,"volume_bid_side":1,"volume_ask_side":0,"volume_no_side":0,"volume_mid_side":0,"iv_low":"0.3204","iv_high":"0.3204","avg_price":"0.12","volume_multi":1,"volume_stock_multi":0},{"close":"0.13","high":"0.13","low":"0.13","open":"0.13","start_time":"2026-05-22T15:44:00Z","premium_mid_side":0,"premium_no_side":0,"premium_ask_side":26,"premium_bid_side":0,"volume_bid_side":0,"volume_ask_side":2,"volume_no_side":0,"volume_mid_side":0,"iv_low":"0.3225","iv_high":"0.3225","avg_price":"0.13","volume_multi":2,"volume_stock_multi":0},{"close":"0.12","high":"0.12","low":"0.12","open":"0.12","start_time":"2026-05-22T15:40:00Z","premium_mid_side":0,"premium_no_side":0,"premium_ask_side":0,"premium_bid_side":24,"volume_bid_side":2,"volume_ask_side":0,"volume_no_side":0,"volume_mid_side":0,"iv_low":"0.3165","iv_high":"0.3165","avg_price":"0.12","volume_multi":2,"volume_stock_multi":0},{"close":"0.11","high":"0.11","low":"0.11","open":"0.11","start_time":"2026-05-22T15:38:00Z","premium_mid_side":0,"premium_no_side":0,"premium_ask_side":0,"premium_bid_side":33,"volume_bid_side":3,"volume_ask_side":0,"volume_no_side":0,"volume_mid_side":0,"iv_low":"0.3110","iv_high":"0.3110","avg_price":"0.11","volume_multi":3,"volume_stock_multi":0},{"close":"0.15","high":"0.15","low":"0.15","open":"0.15","start_time":"2026-05-22T15:37:00Z","premium_mid_side":0,"premium_no_side":0,"premium_ask_side":30,"premium_bid_side":0,"volume_bid_side":0,"volume_ask_side":2,"volume_no_side":0,"volume_mid_side":0,"iv_low":"0.3197","iv_high":"0.3197","avg_price":"0.15","volume_multi":2,"volume_stock_multi":0},{"close":"0.12","high":"0.12","low":"0.12","open":"0.12","start_time":"2026-05-22T15:33:00Z","premium_mid_side":0,"premium_no_side":0,"premium_ask_side":0,"premium_bid_side":216,"volume_bid_side":18,"volume_ask_side":0,"volume_no_side":0,"volume_mid_side":0,"iv_low":"0.3113","iv_high":"0.3114","avg_price":"0.12","volume_multi":18,"volume_stock_multi":0},{"close":"0.12","high":"0.12","low":"0.12","open":"0.12","start_time":"2026-05-22T15:32:00Z","premium_mid_side":0,"premium_no_side":0,"premium_ask_side":0,"premium_bid_side":12,"volume_bid_side":1,"volume_ask_side":0,"volume_no_side":0,"volume_mid_side":0,"iv_low":"0.3102","iv_high":"0.3102","avg_price":"0.12","volume_multi":1,"volume_stock_multi":0},{"close":"0.15","high":"0.15","low":"0.15","open":"0.15","start_time":"2026-05-22T15:31:00Z","premium_mid_side":0,"premium_no_side":0,"premium_ask_side":45,"premium_bid_side":0,"volume_bid_side":0,"volume_ask_side":3,"volume_no_side":0,"volume_mid_side":0,"iv_low":"0.3145","iv_high":"0.3145","avg_price":"0.15","volume_multi":3,"volume_stock_multi":0},{"close":"0.15","high":"0.15","low":"0.12","open":"0.12","start_time":"2026-05-22T15:30:00Z","premium_mid_side":0,"premium_no_side":0,"premium_ask_side":15,"premium_bid_side":48,"volume_bid_side":4,"volume_ask_side":1,"volume_no_side":0,"volume_mid_side":0,"iv_low":"0.3052","iv_high":"0.3151","avg_price":"0.13","volume_multi":5,"volume_stock_multi":0},{"close":"0.12","high":"0.15","low":"0.12","open":"0.15","start_time":"2026-05-22T15:28:00Z","premium_mid_side":0,"premium_no_side":0,"premium_ask_side":45,"premium_bid_side":48,"volume_bid_side":4,"volume_ask_side":3,"volume_no_side":0,"volume_mid_side":0,"iv_low":"0.3079","iv_high":"0.3175","avg_price":"0.13","volume_multi":5,"volume_stock_multi":0},{"close":"0.12","high":"0.15","low":"0.12","open":"0.15","start_time":"2026-05-22T15:27:00Z","premium_mid_side":0,"premium_no_side":0,"premium_ask_side":15,"premium_bid_side":48,"volume_bid_side":4,"volume_ask_side":1,"volume_no_side":0,"volume_mid_side":0,"iv_low":"0.3109","iv_high":"0.3220","avg_price":"0.13","volume_multi":5,"volume_stock_multi":0},{"close":"0.12","high":"0.15","low":"0.12","open":"0.15","start_time":"2026-05-22T15:26:00Z","premium_mid_side":0,"premium_no_side":0,"premium_ask_side":15,"premium_bid_side":60,"volume_bid_side":5,"volume_ask_side":1,"volume_no_side":0,"volume_mid_side":0,"iv_low":"0.3137","iv_high":"0.3215","avg_price":"0.13","volume_multi":5,"volume_stock_multi":0},{"close":"0.15","high":"0.15","low":"0.15","open":"0.15","start_time":"2026-05-22T15:25:00Z","premium_mid_side":0,"premium_no_side":0,"premium_ask_side":15,"premium_bid_side":0,"volume_bid_side":0,"volume_ask_side":1,"volume_no_side":0,"volume_mid_side":0,"iv_low":"0.3262","iv_high":"0.3262","avg_price":"0.15","volume_multi":1,"volume_stock_multi":0},{"close":"0.12","high":"0.12","low":"0.12","open":"0.12","start_time":"2026-05-22T15:23:00Z","premium_mid_side":0,"premium_no_side":0,"premium_ask_side":0,"premium_bid_side":36,"volume_bid_side":3,"volume_ask_side":0,"volume_no_side":0,"volume_mid_side":0,"iv_low":"0.3171","iv_high":"0.3171","avg_price":"0.12","volume_multi":3,"volume_stock_multi":0},{"close":"0.12","high":"0.12","low":"0.12","open":"0.12","start_time":"2026-05-22T15:22:00Z","premium_mid_side":0,"premium_no_side":0,"premium_ask_side":0,"premium_bid_side":36,"volume_bid_side":3,"volume_ask_side":0,"volume_no_side":0,"volume_mid_side":0,"iv_low":"0.3120","iv_high":"0.3120","avg_price":"0.12","volume_multi":3,"volume_stock_multi":0},{"close":"0.12","high":"0.12","low":"0.12","open":"0.12","start_time":"2026-05-22T15:21:00Z","premium_mid_side":0,"premium_no_side":0,"premium_ask_side":0,"premium_bid_side":24,"volume_bid_side":2,"volume_ask_side":0,"volume_no_side":0,"volume_mid_side":0,"iv_low":"0.3138","iv_high":"0.3138","avg_price":"0.12","volume_multi":2,"volume_stock_multi":0},{"close":"0.12","high":"0.12","low":"0.12","open":"0.12","start_time":"2026-05-22T15:20:00Z","premium_mid_side":0,"premium_no_side":0,"premium_ask_side":0,"premium_bid_side":12,"volume_bid_side":1,"volume_ask_side":0,"volume_no_side":0,"volume_mid_side":0,"iv_low":"0.3108","iv_high":"0.3108","avg_price":"0.12","volume_multi":1,"volume_stock_multi":0},{"close":"0.15","high":"0.15","low":"0.15","open":"0.15","start_time":"2026-05-22T15:19:00Z","premium_mid_side":30,"premium_no_side":0,"premium_ask_side":0,"premium_bid_side":0,"volume_bid_side":0,"volume_ask_side":0,"volume_no_side":0,"volume_mid_side":2,"iv_low":"0.3218","iv_high":"0.3218","avg_price":"0.15","volume_multi":2,"volume_stock_multi":0},{"close":"0.15","high":"0.15","low":"0.15","open":"0.15","start_time":"2026-05-22T15:18:00Z","premium_mid_side":15,"premium_no_side":0,"premium_ask_side":0,"premium_bid_side":0,"volume_bid_side":0,"volume_ask_side":0,"volume_no_side":0,"volume_mid_side":1,"iv_low":"0.3242","iv_high":"0.3242","avg_price":"0.15","volume_multi":1,"volume_stock_multi":0},{"close":"0.15","high":"0.15","low":"0.15","open":"0.15","start_time":"2026-05-22T15:17:00Z","premium_mid_side":0,"premium_no_side":0,"premium_ask_side":30,"premium_bid_side":0,"volume_bid_side":0,"volume_ask_side":2,"volume_no_side":0,"volume_mid_side":0,"iv_low":"0.3224","iv_high":"0.3227","avg_price":"0.15","volume_multi":2,"volume_stock_multi":0},{"close":"0.15","high":"0.15","low":"0.13","open":"0.15","start_time":"2026-05-22T15:15:00Z","premium_mid_side":60,"premium_no_side":0,"premium_ask_side":523,"premium_bid_side":0,"volume_bid_side":0,"volume_ask_side":35,"volume_no_side":0,"volume_mid_side":4,"iv_low":"0.3184","iv_high":"0.3257","avg_price":"0.15","volume_multi":35,"volume_stock_multi":0},{"close":"0.13","high":"0.15","low":"0.12","open":"0.12","start_time":"2026-05-22T15:13:00Z","premium_mid_side":0,"premium_no_side":0,"premium_ask_side":54,"premium_bid_side":24,"volume_bid_side":2,"volume_ask_side":4,"volume_no_side":0,"volume_mid_side":0,"iv_low":"0.3162","iv_high":"0.3249","avg_price":"0.13","volume_multi":6,"volume_stock_multi":0},{"close":"0.15","high":"0.15","low":"0.15","open":"0.15","start_time":"2026-05-22T15:12:00Z","premium_mid_side":0,"premium_no_side":0,"premium_ask_side":0,"premium_bid_side":60,"volume_bid_side":4,"volume_ask_side":0,"volume_no_side":0,"volume_mid_side":0,"iv_low":"0.3246","iv_high":"0.3246","avg_price":"0.15","volume_multi":0,"volume_stock_multi":0},{"close":"0.17","high":"0.17","low":"0.17","open":"0.17","start_time":"2026-05-22T15:10:00Z","premium_mid_side":0,"premium_no_side":0,"premium_ask_side":0,"premium_bid_side":34,"volume_bid_side":2,"volume_ask_side":0,"volume_no_side":0,"volume_mid_side":0,"iv_low":"0.3252","iv_high":"0.3252","avg_price":"0.17","volume_multi":2,"volume_stock_multi":0},{"close":"0.17","high":"0.17","low":"0.17","open":"0.17","start_time":"2026-05-22T15:08:00Z","premium_mid_side":0,"premium_no_side":0,"premium_ask_side":0,"premium_bid_side":17,"volume_bid_side":1,"volume_ask_side":0,"volume_no_side":0,"volume_mid_side":0,"iv_low":"0.3296","iv_high":"0.3296","avg_price":"0.17","volume_multi":1,"volume_stock_multi":0},{"close":"0.20","high":"0.20","low":"0.20","open":"0.20","start_time":"2026-05-22T15:07:00Z","premium_mid_side":0,"premium_no_side":0,"premium_ask_side":40,"premium_bid_side":0,"volume_bid_side":0,"volume_ask_side":2,"volume_no_side":0,"volume_mid_side":0,"iv_low":"0.3344","iv_high":"0.3344","avg_price":"0.20","volume_multi":2,"volume_stock_multi":0},{"close":"0.17","high":"0.17","low":"0.17","open":"0.17","start_time":"2026-05-22T15:05:00Z","premium_mid_side":0,"premium_no_side":0,"premium_ask_side":0,"premium_bid_side":34,"volume_bid_side":2,"volume_ask_side":0,"volume_no_side":0,"volume_mid_side":0,"iv_low":"0.3253","iv_high":"0.3253","avg_price":"0.17","volume_multi":2,"volume_stock_multi":0},{"close":"0.17","high":"0.17","low":"0.17","open":"0.17","start_time":"2026-05-22T15:04:00Z","premium_mid_side":0,"premium_no_side":0,"premium_ask_side":0,"premium_bid_side":34,"volume_bid_side":2,"volume_ask_side":0,"volume_no_side":0,"volume_mid_side":0,"iv_low":"0.3305","iv_high":"0.3305","avg_price":"0.17","volume_multi":2,"volume_stock_multi":0},{"close":"0.17","high":"0.17","low":"0.17","open":"0.17","start_time":"2026-05-22T15:03:00Z","premium_mid_side":0,"premium_no_side":0,"premium_ask_side":0,"premium_bid_side":17,"volume_bid_side":1,"volume_ask_side":0,"volume_no_side":0,"volume_mid_side":0,"iv_low":"0.3293","iv_high":"0.3293","avg_price":"0.17","volume_multi":1,"volume_stock_multi":0},{"close":"0.17","high":"0.17","low":"0.15","open":"0.15","start_time":"2026-05-22T15:02:00Z","premium_mid_side":0,"premium_no_side":0,"premium_ask_side":0,"premium_bid_side":199,"volume_bid_side":13,"volume_ask_side":0,"volume_no_side":0,"volume_mid_side":0,"iv_low":"0.3252","iv_high":"0.3308","avg_price":"0.15","volume_multi":2,"volume_stock_multi":0},{"close":"0.17","high":"0.17","low":"0.17","open":"0.17","start_time":"2026-05-22T15:01:00Z","premium_mid_side":0,"premium_no_side":0,"premium_ask_side":0,"premium_bid_side":68,"volume_bid_side":4,"volume_ask_side":0,"volume_no_side":0,"volume_mid_side":0,"iv_low":"0.3312","iv_high":"0.3312","avg_price":"0.17","volume_multi":4,"volume_stock_multi":0},{"close":"0.17","high":"0.18","low":"0.17","open":"0.18","start_time":"2026-05-22T15:00:00Z","premium_mid_side":0,"premium_no_side":0,"premium_ask_side":108,"premium_bid_side":17,"volume_bid_side":1,"volume_ask_side":6,"volume_no_side":0,"volume_mid_side":0,"iv_low":"0.3305","iv_high":"0.3327","avg_price":"0.18","volume_multi":7,"volume_stock_multi":0},{"close":"0.17","high":"0.17","low":"0.17","open":"0.17","start_time":"2026-05-22T14:59:00Z","premium_mid_side":0,"premium_no_side":0,"premium_ask_side":0,"premium_bid_side":85,"volume_bid_side":5,"volume_ask_side":0,"volume_no_side":0,"volume_mid_side":0,"iv_low":"0.3272","iv_high":"0.3272","avg_price":"0.17","volume_multi":5,"volume_stock_multi":0},{"close":"0.17","high":"0.17","low":"0.17","open":"0.17","start_time":"2026-05-22T14:58:00Z","premium_mid_side":0,"premium_no_side":0,"premium_ask_side":0,"premium_bid_side":85,"volume_bid_side":5,"volume_ask_side":0,"volume_no_side":0,"volume_mid_side":0,"iv_low":"0.3293","iv_high":"0.3297","avg_price":"0.17","volume_multi":5,"volume_stock_multi":0},{"close":"0.18","high":"0.20","low":"0.18","open":"0.20","start_time":"2026-05-22T14:57:00Z","premium_mid_side":0,"premium_no_side":0,"premium_ask_side":96,"premium_bid_side":0,"volume_bid_side":0,"volume_ask_side":5,"volume_no_side":0,"volume_mid_side":0,"iv_low":"0.3303","iv_high":"0.3371","avg_price":"0.20","volume_multi":5,"volume_stock_multi":0},{"close":"0.17","high":"0.18","low":"0.17","open":"0.18","start_time":"2026-05-22T14:56:00Z","premium_mid_side":0,"premium_no_side":0,"premium_ask_side":504,"premium_bid_side":17,"volume_bid_side":1,"volume_ask_side":28,"volume_no_side":0,"volume_mid_side":0,"iv_low":"0.3278","iv_high":"0.3346","avg_price":"0.18","volume_multi":29,"volume_stock_multi":0},{"close":"0.17","high":"0.20","low":"0.17","open":"0.20","start_time":"2026-05-22T14:55:00Z","premium_mid_side":0,"premium_no_side":0,"premium_ask_side":38,"premium_bid_side":68,"volume_bid_side":4,"volume_ask_side":2,"volume_no_side":0,"volume_mid_side":0,"iv_low":"0.3338","iv_high":"0.3417","avg_price":"0.18","volume_multi":5,"volume_stock_multi":0},{"close":"0.20","high":"0.20","low":"0.18","open":"0.18","start_time":"2026-05-22T14:53:00Z","premium_mid_side":0,"premium_no_side":0,"premium_ask_side":74,"premium_bid_side":0,"volume_bid_side":0,"volume_ask_side":4,"volume_no_side":0,"volume_mid_side":0,"iv_low":"0.3370","iv_high":"0.3432","avg_price":"0.19","volume_multi":4,"volume_stock_multi":0},{"close":"0.20","high":"0.20","low":"0.20","open":"0.20","start_time":"2026-05-22T14:52:00Z","premium_mid_side":380,"premium_no_side":0,"premium_ask_side":0,"premium_bid_side":0,"volume_bid_side":0,"volume_ask_side":0,"volume_no_side":0,"volume_mid_side":19,"iv_low":"0.3400","iv_high":"0.3408","avg_price":"0.20","volume_multi":19,"volume_stock_multi":0},{"close":"0.20","high":"0.20","low":"0.20","open":"0.20","start_time":"2026-05-22T14:51:00Z","premium_mid_side":20,"premium_no_side":0,"premium_ask_side":560,"premium_bid_side":0,"volume_bid_side":0,"volume_ask_side":28,"volume_no_side":0,"volume_mid_side":1,"iv_low":"0.3398","iv_high":"0.3410","avg_price":"0.20","volume_multi":29,"volume_stock_multi":0},{"close":"0.20","high":"0.20","low":"0.20","open":"0.20","start_time":"2026-05-22T14:50:00Z","premium_mid_side":0,"premium_no_side":0,"premium_ask_side":20,"premium_bid_side":0,"volume_bid_side":0,"volume_ask_side":1,"volume_no_side":0,"volume_mid_side":0,"iv_low":"0.3386","iv_high":"0.3386","avg_price":"0.20","volume_multi":1,"volume_stock_multi":0},{"close":"0.17","high":"0.22","low":"0.17","open":"0.20","start_time":"2026-05-22T14:49:00Z","premium_mid_side":40,"premium_no_side":0,"premium_ask_side":22,"premium_bid_side":17,"volume_bid_side":1,"volume_ask_side":1,"volume_no_side":0,"volume_mid_side":2,"iv_low":"0.3298","iv_high":"0.3367","avg_price":"0.20","volume_multi":4,"volume_stock_multi":0},{"close":"0.20","high":"0.20","low":"0.20","open":"0.20","start_time":"2026-05-22T14:48:00Z","premium_mid_side":0,"premium_no_side":0,"premium_ask_side":240,"premium_bid_side":0,"volume_bid_side":0,"volume_ask_side":12,"volume_no_side":0,"volume_mid_side":0,"iv_low":"0.3351","iv_high":"0.3351","avg_price":"0.20","volume_multi":0,"volume_stock_multi":0},{"close":"0.20","high":"0.20","low":"0.17","open":"0.20","start_time":"2026-05-22T14:47:00Z","premium_mid_side":0,"premium_no_side":0,"premium_ask_side":544,"premium_bid_side":17,"volume_bid_side":1,"volume_ask_side":30,"volume_no_side":0,"volume_mid_side":0,"iv_low":"0.3349","iv_high":"0.3435","avg_price":"0.18","volume_multi":31,"volume_stock_multi":0},{"close":"0.25","high":"0.25","low":"0.25","open":"0.25","start_time":"2026-05-22T14:45:00Z","premium_mid_side":0,"premium_no_side":0,"premium_ask_side":50,"premium_bid_side":0,"volume_bid_side":0,"volume_ask_side":2,"volume_no_side":0,"volume_mid_side":0,"iv_low":"0.3400","iv_high":"0.3400","avg_price":"0.25","volume_multi":2,"volume_stock_multi":0},{"close":"0.24","high":"0.24","low":"0.24","open":"0.24","start_time":"2026-05-22T14:44:00Z","premium_mid_side":0,"premium_no_side":0,"premium_ask_side":48,"premium_bid_side":0,"volume_bid_side":0,"volume_ask_side":2,"volume_no_side":0,"volume_mid_side":0,"iv_low":"0.3383","iv_high":"0.3383","avg_price":"0.24","volume_multi":2,"volume_stock_multi":0},{"close":"0.22","high":"0.22","low":"0.22","open":"0.22","start_time":"2026-05-22T14:43:00Z","premium_mid_side":0,"premium_no_side":0,"premium_ask_side":0,"premium_bid_side":44,"volume_bid_side":2,"volume_ask_side":0,"volume_no_side":0,"volume_mid_side":0,"iv_low":"0.3333","iv_high":"0.3333","avg_price":"0.22","volume_multi":2,"volume_stock_multi":0},{"close":"0.20","high":"0.20","low":"0.20","open":"0.20","start_time":"2026-05-22T14:41:00Z","premium_mid_side":0,"premium_no_side":0,"premium_ask_side":0,"premium_bid_side":100,"volume_bid_side":5,"volume_ask_side":0,"volume_no_side":0,"volume_mid_side":0,"iv_low":"0.3318","iv_high":"0.3318","avg_price":"0.20","volume_multi":5,"volume_stock_multi":0},{"close":"0.20","high":"0.22","low":"0.20","open":"0.20","start_time":"2026-05-22T14:40:00Z","premium_mid_side":20,"premium_no_side":0,"premium_ask_side":140,"premium_bid_side":620,"volume_bid_side":30,"volume_ask_side":7,"volume_no_side":0,"volume_mid_side":1,"iv_low":"0.3306","iv_high":"0.3354","avg_price":"0.21","volume_multi":20,"volume_stock_multi":0},{"close":"0.20","high":"0.20","low":"0.20","open":"0.20","start_time":"2026-05-22T14:39:00Z","premium_mid_side":0,"premium_no_side":0,"premium_ask_side":40,"premium_bid_side":0,"volume_bid_side":0,"volume_ask_side":2,"volume_no_side":0,"volume_mid_side":0,"iv_low":"0.3312","iv_high":"0.3312","avg_price":"0.20","volume_multi":2,"volume_stock_multi":0},{"close":"0.17","high":"0.17","low":"0.17","open":"0.17","start_time":"2026-05-22T14:38:00Z","premium_mid_side":0,"premium_no_side":0,"premium_ask_side":0,"premium_bid_side":34,"volume_bid_side":2,"volume_ask_side":0,"volume_no_side":0,"volume_mid_side":0,"iv_low":"0.3249","iv_high":"0.3267","avg_price":"0.17","volume_multi":2,"volume_stock_multi":0},{"close":"0.20","high":"0.20","low":"0.18","open":"0.18","start_time":"2026-05-22T14:37:00Z","premium_mid_side":0,"premium_no_side":0,"premium_ask_side":526,"premium_bid_side":0,"volume_bid_side":0,"volume_ask_side":29,"volume_no_side":0,"volume_mid_side":0,"iv_low":"0.3263","iv_high":"0.3306","avg_price":"0.18","volume_multi":29,"volume_stock_multi":0},{"close":"0.20","high":"0.20","low":"0.20","open":"0.20","start_time":"2026-05-22T14:36:00Z","premium_mid_side":0,"premium_no_side":0,"premium_ask_side":20,"premium_bid_side":0,"volume_bid_side":0,"volume_ask_side":1,"volume_no_side":0,"volume_mid_side":0,"iv_low":"0.3335","iv_high":"0.3335","avg_price":"0.20","volume_multi":1,"volume_stock_multi":0},{"close":"0.20","high":"0.20","low":"0.17","open":"0.20","start_time":"2026-05-22T14:35:00Z","premium_mid_side":0,"premium_no_side":0,"premium_ask_side":38,"premium_bid_side":2017,"volume_bid_side":101,"volume_ask_side":2,"volume_no_side":0,"volume_mid_side":0,"iv_low":"0.3282","iv_high":"0.3364","avg_price":"0.20","volume_multi":3,"volume_stock_multi":0},{"close":"0.20","high":"0.20","low":"0.20","open":"0.20","start_time":"2026-05-22T14:34:00Z","premium_mid_side":0,"premium_no_side":0,"premium_ask_side":480,"premium_bid_side":0,"volume_bid_side":0,"volume_ask_side":24,"volume_no_side":0,"volume_mid_side":0,"iv_low":"0.3363","iv_high":"0.3377","avg_price":"0.20","volume_multi":2,"volume_stock_multi":0},{"close":"0.17","high":"0.20","low":"0.17","open":"0.20","start_time":"2026-05-22T14:32:00Z","premium_mid_side":0,"premium_no_side":0,"premium_ask_side":20,"premium_bid_side":102,"volume_bid_side":6,"volume_ask_side":1,"volume_no_side":0,"volume_mid_side":0,"iv_low":"0.3320","iv_high":"0.3361","avg_price":"0.18","volume_multi":7,"volume_stock_multi":0},{"close":"0.17","high":"0.17","low":"0.17","open":"0.17","start_time":"2026-05-22T14:31:00Z","premium_mid_side":0,"premium_no_side":0,"premium_ask_side":0,"premium_bid_side":68,"volume_bid_side":4,"volume_ask_side":0,"volume_no_side":0,"volume_mid_side":0,"iv_low":"0.3294","iv_high":"0.3321","avg_price":"0.17","volume_multi":4,"volume_stock_multi":0},{"close":"0.17","high":"0.20","low":"0.17","open":"0.20","start_time":"2026-05-22T14:30:00Z","premium_mid_side":0,"premium_no_side":0,"premium_ask_side":20,"premium_bid_side":17,"volume_bid_side":1,"volume_ask_side":1,"volume_no_side":0,"volume_mid_side":0,"iv_low":"0.3332","iv_high":"0.3379","avg_price":"0.19","volume_multi":2,"volume_stock_multi":0},{"close":"0.17","high":"0.17","low":"0.17","open":"0.17","start_time":"2026-05-22T14:29:00Z","premium_mid_side":0,"premium_no_side":0,"premium_ask_side":0,"premium_bid_side":34,"volume_bid_side":2,"volume_ask_side":0,"volume_no_side":0,"volume_mid_side":0,"iv_low":"0.3323","iv_high":"0.3355","avg_price":"0.17","volume_multi":2,"volume_stock_multi":0},{"close":"0.15","high":"0.15","low":"0.15","open":"0.15","start_time":"2026-05-22T14:28:00Z","premium_mid_side":0,"premium_no_side":0,"premium_ask_side":0,"premium_bid_side":30,"volume_bid_side":2,"volume_ask_side":0,"volume_no_side":0,"volume_mid_side":0,"iv_low":"0.3321","iv_high":"0.3321","avg_price":"0.15","volume_multi":2,"volume_stock_multi":0},{"close":"0.15","high":"0.15","low":"0.15","open":"0.15","start_time":"2026-05-22T14:27:00Z","premium_mid_side":60,"premium_no_side":0,"premium_ask_side":420,"premium_bid_side":0,"volume_bid_side":0,"volume_ask_side":28,"volume_no_side":0,"volume_mid_side":4,"iv_low":"0.3331","iv_high":"0.3344","avg_price":"0.15","volume_multi":32,"volume_stock_multi":0},{"close":"0.12","high":"0.12","low":"0.12","open":"0.12","start_time":"2026-05-22T14:26:00Z","premium_mid_side":0,"premium_no_side":0,"premium_ask_side":0,"premium_bid_side":60,"volume_bid_side":5,"volume_ask_side":0,"volume_no_side":0,"volume_mid_side":0,"iv_low":"0.3220","iv_high":"0.3228","avg_price":"0.12","volume_multi":5,"volume_stock_multi":0},{"close":"0.15","high":"0.15","low":"0.12","open":"0.12","start_time":"2026-05-22T14:25:00Z","premium_mid_side":0,"premium_no_side":0,"premium_ask_side":75,"premium_bid_side":24,"volume_bid_side":2,"volume_ask_side":5,"volume_no_side":0,"volume_mid_side":0,"iv_low":"0.3296","iv_high":"0.3381","avg_price":"0.14","volume_multi":7,"volume_stock_multi":0},{"close":"0.12","high":"0.15","low":"0.12","open":"0.15","start_time":"2026-05-22T14:24:00Z","premium_mid_side":810,"premium_no_side":0,"premium_ask_side":150,"premium_bid_side":84,"volume_bid_side":7,"volume_ask_side":10,"volume_no_side":0,"volume_mid_side":54,"iv_low":"0.3288","iv_high":"0.3439","avg_price":"0.15","volume_multi":71,"volume_stock_multi":0},{"close":"0.12","high":"0.15","low":"0.12","open":"0.13","start_time":"2026-05-22T14:23:00Z","premium_mid_side":0,"premium_no_side":0,"premium_ask_side":248,"premium_bid_side":120,"volume_bid_side":10,"volume_ask_side":18,"volume_no_side":0,"volume_mid_side":0,"iv_low":"0.3312","iv_high":"0.3394","avg_price":"0.13","volume_multi":27,"volume_stock_multi":0},{"close":"0.12","high":"0.15","low":"0.12","open":"0.15","start_time":"2026-05-22T14:22:00Z","premium_mid_side":0,"premium_no_side":0,"premium_ask_side":264,"premium_bid_side":96,"volume_bid_side":8,"volume_ask_side":18,"volume_no_side":0,"volume_mid_side":0,"iv_low":"0.3249","iv_high":"0.3358","avg_price":"0.14","volume_multi":21,"volume_stock_multi":0},{"close":"0.15","high":"0.15","low":"0.15","open":"0.15","start_time":"2026-05-22T14:21:00Z","premium_mid_side":0,"premium_no_side":0,"premium_ask_side":150,"premium_bid_side":300,"volume_bid_side":20,"volume_ask_side":10,"volume_no_side":0,"volume_mid_side":0,"iv_low":"0.3289","iv_high":"0.3296","avg_price":"0.15","volume_multi":10,"volume_stock_multi":0},{"close":"0.15","high":"0.17","low":"0.15","open":"0.17","start_time":"2026-05-22T14:20:00Z","premium_mid_side":150,"premium_no_side":0,"premium_ask_side":0,"premium_bid_side":1551,"volume_bid_side":103,"volume_ask_side":0,"volume_no_side":0,"volume_mid_side":10,"iv_low":"0.3251","iv_high":"0.3325","avg_price":"0.15","volume_multi":3,"volume_stock_multi":0},{"close":"0.15","high":"0.18","low":"0.15","open":"0.18","start_time":"2026-05-22T14:19:00Z","premium_mid_side":0,"premium_no_side":0,"premium_ask_side":36,"premium_bid_side":60,"volume_bid_side":4,"volume_ask_side":2,"volume_no_side":0,"volume_mid_side":0,"iv_low":"0.3250","iv_high":"0.3318","avg_price":"0.16","volume_multi":2,"volume_stock_multi":0},{"close":"0.15","high":"0.15","low":"0.15","open":"0.15","start_time":"2026-05-22T14:18:00Z","premium_mid_side":0,"premium_no_side":0,"premium_ask_side":0,"premium_bid_side":120,"volume_bid_side":8,"volume_ask_side":0,"volume_no_side":0,"volume_mid_side":0,"iv_low":"0.3193","iv_high":"0.3235","avg_price":"0.15","volume_multi":2,"volume_stock_multi":0},{"close":"0.15","high":"0.18","low":"0.15","open":"0.18","start_time":"2026-05-22T14:17:00Z","premium_mid_side":0,"premium_no_side":0,"premium_ask_side":18,"premium_bid_side":105,"volume_bid_side":7,"volume_ask_side":1,"volume_no_side":0,"volume_mid_side":0,"iv_low":"0.3154","iv_high":"0.3231","avg_price":"0.16","volume_multi":3,"volume_stock_multi":0},{"close":"0.15","high":"0.15","low":"0.15","open":"0.15","start_time":"2026-05-22T14:16:00Z","premium_mid_side":0,"premium_no_side":0,"premium_ask_side":0,"premium_bid_side":150,"volume_bid_side":10,"volume_ask_side":0,"volume_no_side":0,"volume_mid_side":0,"iv_low":"0.3157","iv_high":"0.3157","avg_price":"0.15","volume_multi":10,"volume_stock_multi":0},{"close":"0.15","high":"0.17","low":"0.12","open":"0.15","start_time":"2026-05-22T14:15:00Z","premium_mid_side":210,"premium_no_side":0,"premium_ask_side":190,"premium_bid_side":138,"volume_bid_side":9,"volume_ask_side":14,"volume_no_side":0,"volume_mid_side":14,"iv_low":"0.3060","iv_high":"0.3254","avg_price":"0.15","volume_multi":37,"volume_stock_multi":0},{"close":"0.15","high":"0.17","low":"0.15","open":"0.17","start_time":"2026-05-22T14:14:00Z","premium_mid_side":255,"premium_no_side":0,"premium_ask_side":0,"premium_bid_side":199,"volume_bid_side":13,"volume_ask_side":0,"volume_no_side":0,"volume_mid_side":17,"iv_low":"0.3196","iv_high":"0.3226","avg_price":"0.15","volume_multi":3,"volume_stock_multi":0},{"close":"0.17","high":"0.17","low":"0.15","open":"0.15","start_time":"2026-05-22T14:13:00Z","premium_mid_side":0,"premium_no_side":0,"premium_ask_side":0,"premium_bid_side":402,"volume_bid_side":26,"volume_ask_side":0,"volume_no_side":0,"volume_mid_side":0,"iv_low":"0.3135","iv_high":"0.3218","avg_price":"0.15","volume_multi":26,"volume_stock_multi":0},{"close":"0.15","high":"0.15","low":"0.15","open":"0.15","start_time":"2026-05-22T14:12:00Z","premium_mid_side":0,"premium_no_side":0,"premium_ask_side":0,"premium_bid_side":30,"volume_bid_side":2,"volume_ask_side":0,"volume_no_side":0,"volume_mid_side":0,"iv_low":"0.3072","iv_high":"0.3087","avg_price":"0.15","volume_multi":1,"volume_stock_multi":0},{"close":"0.15","high":"0.17","low":"0.15","open":"0.17","start_time":"2026-05-22T14:11:00Z","premium_mid_side":0,"premium_no_side":0,"premium_ask_side":0,"premium_bid_side":111,"volume_bid_side":7,"volume_ask_side":0,"volume_no_side":0,"volume_mid_side":0,"iv_low":"0.3081","iv_high":"0.3126","avg_price":"0.16","volume_multi":3,"volume_stock_multi":0},{"close":"0.15","high":"0.20","low":"0.15","open":"0.15","start_time":"2026-05-22T14:10:00Z","premium_mid_side":615,"premium_no_side":0,"premium_ask_side":1490,"premium_bid_side":60,"volume_bid_side":4,"volume_ask_side":78,"volume_no_side":0,"volume_mid_side":41,"iv_low":"0.3042","iv_high":"0.3187","avg_price":"0.18","volume_multi":5,"volume_stock_multi":0},{"close":"0.12","high":"0.15","low":"0.12","open":"0.15","start_time":"2026-05-22T14:09:00Z","premium_mid_side":0,"premium_no_side":0,"premium_ask_side":30,"premium_bid_side":12,"volume_bid_side":1,"volume_ask_side":2,"volume_no_side":0,"volume_mid_side":0,"iv_low":"0.3018","iv_high":"0.3098","avg_price":"0.14","volume_multi":3,"volume_stock_multi":0},{"close":"0.15","high":"0.15","low":"0.15","open":"0.15","start_time":"2026-05-22T14:08:00Z","premium_mid_side":0,"premium_no_side":0,"premium_ask_side":45,"premium_bid_side":0,"volume_bid_side":0,"volume_ask_side":3,"volume_no_side":0,"volume_mid_side":0,"iv_low":"0.3092","iv_high":"0.3099","avg_price":"0.15","volume_multi":1,"volume_stock_multi":0},{"close":"0.13","high":"0.13","low":"0.12","open":"0.12","start_time":"2026-05-22T14:07:00Z","premium_mid_side":0,"premium_no_side":0,"premium_ask_side":26,"premium_bid_side":36,"volume_bid_side":3,"volume_ask_side":2,"volume_no_side":0,"volume_mid_side":0,"iv_low":"0.3012","iv_high":"0.3031","avg_price":"0.12","volume_multi":5,"volume_stock_multi":0},{"close":"0.12","high":"0.12","low":"0.12","open":"0.12","start_time":"2026-05-22T14:06:00Z","premium_mid_side":0,"premium_no_side":0,"premium_ask_side":0,"premium_bid_side":108,"volume_bid_side":9,"volume_ask_side":0,"volume_no_side":0,"volume_mid_side":0,"iv_low":"0.3057","iv_high":"0.3075","avg_price":"0.12","volume_multi":9,"volume_stock_multi":0},{"close":"0.15","high":"0.15","low":"0.12","open":"0.12","start_time":"2026-05-22T14:05:00Z","premium_mid_side":0,"premium_no_side":0,"premium_ask_side":45,"premium_bid_side":96,"volume_bid_side":8,"volume_ask_side":3,"volume_no_side":0,"volume_mid_side":0,"iv_low":"0.2987","iv_high":"0.3157","avg_price":"0.13","volume_multi":11,"volume_stock_multi":0},{"close":"0.12","high":"0.12","low":"0.12","open":"0.12","start_time":"2026-05-22T14:04:00Z","premium_mid_side":0,"premium_no_side":0,"premium_ask_side":0,"premium_bid_side":24,"volume_bid_side":2,"volume_ask_side":0,"volume_no_side":0,"volume_mid_side":0,"iv_low":"0.2970","iv_high":"0.2970","avg_price":"0.12","volume_multi":2,"volume_stock_multi":0},{"close":"0.12","high":"0.12","low":"0.12","open":"0.12","start_time":"2026-05-22T14:03:00Z","premium_mid_side":0,"premium_no_side":0,"premium_ask_side":0,"premium_bid_side":12,"volume_bid_side":1,"volume_ask_side":0,"volume_no_side":0,"volume_mid_side":0,"iv_low":"0.2955","iv_high":"0.2955","avg_price":"0.12","volume_multi":1,"volume_stock_multi":0},{"close":"0.12","high":"0.15","low":"0.10","open":"0.12","start_time":"2026-05-22T14:02:00Z","premium_mid_side":0,"premium_no_side":0,"premium_ask_side":15,"premium_bid_side":154,"volume_bid_side":13,"volume_ask_side":1,"volume_no_side":0,"volume_mid_side":0,"iv_low":"0.2913","iv_high":"0.3053","avg_price":"0.12","volume_multi":13,"volume_stock_multi":0},{"close":"0.12","high":"0.15","low":"0.12","open":"0.12","start_time":"2026-05-22T14:00:00Z","premium_mid_side":0,"premium_no_side":0,"premium_ask_side":135,"premium_bid_side":312,"volume_bid_side":26,"volume_ask_side":9,"volume_no_side":0,"volume_mid_side":0,"iv_low":"0.2787","iv_high":"0.2893","avg_price":"0.13","volume_multi":35,"volume_stock_multi":0},{"close":"0.12","high":"0.15","low":"0.12","open":"0.15","start_time":"2026-05-22T13:59:00Z","premium_mid_side":0,"premium_no_side":0,"premium_ask_side":15,"premium_bid_side":48,"volume_bid_side":4,"volume_ask_side":1,"volume_no_side":0,"volume_mid_side":0,"iv_low":"0.2733","iv_high":"0.2828","avg_price":"0.13","volume_multi":4,"volume_stock_multi":0},{"close":"0.12","high":"0.12","low":"0.12","open":"0.12","start_time":"2026-05-22T13:56:00Z","premium_mid_side":0,"premium_no_side":0,"premium_ask_side":0,"premium_bid_side":12,"volume_bid_side":1,"volume_ask_side":0,"volume_no_side":0,"volume_mid_side":0,"iv_low":"0.2793","iv_high":"0.2793","avg_price":"0.12","volume_multi":1,"volume_stock_multi":0},{"close":"0.15","high":"0.15","low":"0.13","open":"0.13","start_time":"2026-05-22T13:55:00Z","premium_mid_side":0,"premium_no_side":0,"premium_ask_side":58,"premium_bid_side":0,"volume_bid_side":0,"volume_ask_side":4,"volume_no_side":0,"volume_mid_side":0,"iv_low":"0.2740","iv_high":"0.2871","avg_price":"0.15","volume_multi":3,"volume_stock_multi":0},{"close":"0.12","high":"0.15","low":"0.12","open":"0.12","start_time":"2026-05-22T13:54:00Z","premium_mid_side":0,"premium_no_side":0,"premium_ask_side":15,"premium_bid_side":120,"volume_bid_side":10,"volume_ask_side":1,"volume_no_side":0,"volume_mid_side":0,"iv_low":"0.2744","iv_high":"0.2818","avg_price":"0.12","volume_multi":11,"volume_stock_multi":0},{"close":"0.12","high":"0.15","low":"0.12","open":"0.12","start_time":"2026-05-22T13:51:00Z","premium_mid_side":0,"premium_no_side":0,"premium_ask_side":15,"premium_bid_side":180,"volume_bid_side":15,"volume_ask_side":1,"volume_no_side":0,"volume_mid_side":0,"iv_low":"0.2757","iv_high":"0.2822","avg_price":"0.12","volume_multi":16,"volume_stock_multi":0},{"close":"0.15","high":"0.15","low":"0.15","open":"0.15","start_time":"2026-05-22T13:50:00Z","premium_mid_side":495,"premium_no_side":0,"premium_ask_side":15,"premium_bid_side":0,"volume_bid_side":0,"volume_ask_side":1,"volume_no_side":0,"volume_mid_side":33,"iv_low":"0.2758","iv_high":"0.2837","avg_price":"0.15","volume_multi":1,"volume_stock_multi":0},{"close":"0.15","high":"0.15","low":"0.12","open":"0.13","start_time":"2026-05-22T13:49:00Z","premium_mid_side":0,"premium_no_side":0,"premium_ask_side":949,"premium_bid_side":24,"volume_bid_side":2,"volume_ask_side":67,"volume_no_side":0,"volume_mid_side":0,"iv_low":"0.2722","iv_high":"0.2806","avg_price":"0.14","volume_multi":31,"volume_stock_multi":0},{"close":"0.15","high":"0.15","low":"0.15","open":"0.15","start_time":"2026-05-22T13:48:00Z","premium_mid_side":0,"premium_no_side":0,"premium_ask_side":435,"premium_bid_side":0,"volume_bid_side":0,"volume_ask_side":29,"volume_no_side":0,"volume_mid_side":0,"iv_low":"0.2665","iv_high":"0.2795","avg_price":"0.15","volume_multi":21,"volume_stock_multi":0},{"close":"0.12","high":"0.12","low":"0.12","open":"0.12","start_time":"2026-05-22T13:47:00Z","premium_mid_side":0,"premium_no_side":0,"premium_ask_side":0,"premium_bid_side":12,"volume_bid_side":1,"volume_ask_side":0,"volume_no_side":0,"volume_mid_side":0,"iv_low":"0.2589","iv_high":"0.2589","avg_price":"0.12","volume_multi":1,"volume_stock_multi":0},{"close":"0.15","high":"0.15","low":"0.15","open":"0.15","start_time":"2026-05-22T13:46:00Z","premium_mid_side":0,"premium_no_side":0,"premium_ask_side":30,"premium_bid_side":0,"volume_bid_side":0,"volume_ask_side":2,"volume_no_side":0,"volume_mid_side":0,"iv_low":"0.2642","iv_high":"0.2644","avg_price":"0.15","volume_multi":1,"volume_stock_multi":0},{"close":"0.12","high":"0.15","low":"0.12","open":"0.15","start_time":"2026-05-22T13:45:00Z","premium_mid_side":0,"premium_no_side":0,"premium_ask_side":836,"premium_bid_side":120,"volume_bid_side":10,"volume_ask_side":56,"volume_no_side":0,"volume_mid_side":0,"iv_low":"0.2575","iv_high":"0.2692","avg_price":"0.15","volume_multi":65,"volume_stock_multi":0},{"close":"0.12","high":"0.15","low":"0.12","open":"0.15","start_time":"2026-05-22T13:44:00Z","premium_mid_side":0,"premium_no_side":0,"premium_ask_side":435,"premium_bid_side":48,"volume_bid_side":4,"volume_ask_side":29,"volume_no_side":0,"volume_mid_side":0,"iv_low":"0.2622","iv_high":"0.2743","avg_price":"0.15","volume_multi":32,"volume_stock_multi":0},{"close":"0.12","high":"0.15","low":"0.12","open":"0.12","start_time":"2026-05-22T13:43:00Z","premium_mid_side":0,"premium_no_side":0,"premium_ask_side":75,"premium_bid_side":564,"volume_bid_side":47,"volume_ask_side":5,"volume_no_side":0,"volume_mid_side":0,"iv_low":"0.2614","iv_high":"0.2691","avg_price":"0.12","volume_multi":52,"volume_stock_multi":0},{"close":"0.12","high":"0.15","low":"0.10","open":"0.13","start_time":"2026-05-22T13:42:00Z","premium_mid_side":0,"premium_no_side":0,"premium_ask_side":208,"premium_bid_side":274,"volume_bid_side":23,"volume_ask_side":14,"volume_no_side":0,"volume_mid_side":0,"iv_low":"0.2602","iv_high":"0.2745","avg_price":"0.13","volume_multi":33,"volume_stock_multi":0},{"close":"0.15","high":"0.15","low":"0.12","open":"0.12","start_time":"2026-05-22T13:41:00Z","premium_mid_side":0,"premium_no_side":0,"premium_ask_side":150,"premium_bid_side":180,"volume_bid_side":15,"volume_ask_side":10,"volume_no_side":0,"volume_mid_side":0,"iv_low":"0.2603","iv_high":"0.2722","avg_price":"0.13","volume_multi":25,"volume_stock_multi":0},{"close":"0.15","high":"0.15","low":"0.12","open":"0.12","start_time":"2026-05-22T13:40:00Z","premium_mid_side":0,"premium_no_side":0,"premium_ask_side":465,"premium_bid_side":24,"volume_bid_side":2,"volume_ask_side":31,"volume_no_side":0,"volume_mid_side":0,"iv_low":"0.2575","iv_high":"0.2696","avg_price":"0.15","volume_multi":2,"volume_stock_multi":0},{"close":"0.15","high":"0.15","low":"0.12","open":"0.12","start_time":"2026-05-22T13:39:00Z","premium_mid_side":0,"premium_no_side":0,"premium_ask_side":90,"premium_bid_side":12,"volume_bid_side":1,"volume_ask_side":6,"volume_no_side":0,"volume_mid_side":0,"iv_low":"0.2584","iv_high":"0.2677","avg_price":"0.15","volume_multi":7,"volume_stock_multi":0},{"close":"0.15","high":"0.15","low":"0.15","open":"0.15","start_time":"2026-05-22T13:38:00Z","premium_mid_side":0,"premium_no_side":0,"premium_ask_side":570,"premium_bid_side":0,"volume_bid_side":0,"volume_ask_side":38,"volume_no_side":0,"volume_mid_side":0,"iv_low":"0.2651","iv_high":"0.2687","avg_price":"0.15","volume_multi":5,"volume_stock_multi":0},{"close":"0.12","high":"0.15","low":"0.12","open":"0.15","start_time":"2026-05-22T13:37:00Z","premium_mid_side":0,"premium_no_side":0,"premium_ask_side":1080,"premium_bid_side":168,"volume_bid_side":14,"volume_ask_side":72,"volume_no_side":0,"volume_mid_side":0,"iv_low":"0.2600","iv_high":"0.2722","avg_price":"0.15","volume_multi":17,"volume_stock_multi":0},{"close":"0.15","high":"0.15","low":"0.10","open":"0.12","start_time":"2026-05-22T13:36:00Z","premium_mid_side":0,"premium_no_side":0,"premium_ask_side":195,"premium_bid_side":22,"volume_bid_side":2,"volume_ask_side":13,"volume_no_side":0,"volume_mid_side":0,"iv_low":"0.2611","iv_high":"0.2728","avg_price":"0.15","volume_multi":6,"volume_stock_multi":0},{"close":"0.12","high":"0.15","low":"0.12","open":"0.13","start_time":"2026-05-22T13:35:00Z","premium_mid_side":0,"premium_no_side":0,"premium_ask_side":28,"premium_bid_side":12,"volume_bid_side":1,"volume_ask_side":2,"volume_no_side":0,"volume_mid_side":0,"iv_low":"0.2664","iv_high":"0.2732","avg_price":"0.13","volume_multi":3,"volume_stock_multi":0},{"close":"0.12","high":"0.12","low":"0.12","open":"0.12","start_time":"2026-05-22T13:34:00Z","premium_mid_side":0,"premium_no_side":0,"premium_ask_side":0,"premium_bid_side":240,"volume_bid_side":20,"volume_ask_side":0,"volume_no_side":0,"volume_mid_side":0,"iv_low":"0.2688","iv_high":"0.2688","avg_price":"0.12","volume_multi":20,"volume_stock_multi":0},{"close":"0.12","high":"0.15","low":"0.10","open":"0.10","start_time":"2026-05-22T13:33:00Z","premium_mid_side":0,"premium_no_side":0,"premium_ask_side":150,"premium_bid_side":106,"volume_bid_side":9,"volume_ask_side":10,"volume_no_side":0,"volume_mid_side":0,"iv_low":"0.2623","iv_high":"0.2785","avg_price":"0.14","volume_multi":18,"volume_stock_multi":0},{"close":"0.15","high":"0.15","low":"0.12","open":"0.12","start_time":"2026-05-22T13:32:00Z","premium_mid_side":0,"premium_no_side":0,"premium_ask_side":150,"premium_bid_side":276,"volume_bid_side":23,"volume_ask_side":10,"volume_no_side":0,"volume_mid_side":0,"iv_low":"0.2650","iv_high":"0.2740","avg_price":"0.13","volume_multi":33,"volume_stock_multi":0},{"close":"0.15","high":"0.15","low":"0.15","open":"0.15","start_time":"2026-05-22T13:30:00Z","premium_mid_side":0,"premium_no_side":0,"premium_ask_side":150,"premium_bid_side":0,"volume_bid_side":0,"volume_ask_side":10,"volume_no_side":0,"volume_mid_side":0,"iv_low":"0.2952","iv_high":"0.2952","avg_price":"0.15","volume_multi":0,"volume_stock_multi":0}]