[{"close":"0.01","high":"0.01","low":"0.01","open":"0.01","start_time":"2026-05-05T19:49:00Z","avg_price":"0.01","iv_high":"0.9566","iv_low":"0.9566","premium_ask_side":1,"premium_bid_side":0,"premium_mid_side":0,"premium_no_side":0,"volume_ask_side":1,"volume_bid_side":0,"volume_mid_side":0,"volume_no_side":0,"volume_multi":1,"volume_stock_multi":0},{"close":"0.01","high":"0.01","low":"0.01","open":"0.01","start_time":"2026-05-05T19:46:00Z","avg_price":"0.01","iv_high":"0.8243","iv_low":"0.8243","premium_ask_side":2,"premium_bid_side":0,"premium_mid_side":0,"premium_no_side":0,"volume_ask_side":2,"volume_bid_side":0,"volume_mid_side":0,"volume_no_side":0,"volume_multi":0,"volume_stock_multi":0},{"close":"0.01","high":"0.01","low":"0.01","open":"0.01","start_time":"2026-05-05T19:45:00Z","avg_price":"0.01","iv_high":"0.8189","iv_low":"0.8034","premium_ask_side":18,"premium_bid_side":0,"premium_mid_side":0,"premium_no_side":0,"volume_ask_side":18,"volume_bid_side":0,"volume_mid_side":0,"volume_no_side":0,"volume_multi":4,"volume_stock_multi":0},{"close":"0.01","high":"0.01","low":"0.01","open":"0.01","start_time":"2026-05-05T19:36:00Z","avg_price":"0.01","iv_high":"0.6496","iv_low":"0.6496","premium_ask_side":1,"premium_bid_side":0,"premium_mid_side":0,"premium_no_side":0,"volume_ask_side":1,"volume_bid_side":0,"volume_mid_side":0,"volume_no_side":0,"volume_multi":1,"volume_stock_multi":0},{"close":"0.01","high":"0.01","low":"0.01","open":"0.01","start_time":"2026-05-05T19:34:00Z","avg_price":"0.01","iv_high":"0.6077","iv_low":"0.6077","premium_ask_side":20,"premium_bid_side":0,"premium_mid_side":0,"premium_no_side":0,"volume_ask_side":20,"volume_bid_side":0,"volume_mid_side":0,"volume_no_side":0,"volume_multi":20,"volume_stock_multi":0},{"close":"0.01","high":"0.01","low":"0.01","open":"0.01","start_time":"2026-05-05T19:08:00Z","avg_price":"0.01","iv_high":"0.4343","iv_low":"0.4343","premium_ask_side":19,"premium_bid_side":0,"premium_mid_side":0,"premium_no_side":0,"volume_ask_side":19,"volume_bid_side":0,"volume_mid_side":0,"volume_no_side":0,"volume_multi":19,"volume_stock_multi":0},{"close":"0.01","high":"0.01","low":"0.01","open":"0.01","start_time":"2026-05-05T18:50:00Z","avg_price":"0.01","iv_high":"0.3842","iv_low":"0.3842","premium_ask_side":9,"premium_bid_side":0,"premium_mid_side":0,"premium_no_side":0,"volume_ask_side":9,"volume_bid_side":0,"volume_mid_side":0,"volume_no_side":0,"volume_multi":9,"volume_stock_multi":0},{"close":"0.01","high":"0.01","low":"0.01","open":"0.01","start_time":"2026-05-05T18:45:00Z","avg_price":"0.01","iv_high":"0.3775","iv_low":"0.3774","premium_ask_side":3,"premium_bid_side":0,"premium_mid_side":0,"premium_no_side":0,"volume_ask_side":3,"volume_bid_side":0,"volume_mid_side":0,"volume_no_side":0,"volume_multi":3,"volume_stock_multi":0},{"close":"0.01","high":"0.01","low":"0.01","open":"0.01","start_time":"2026-05-05T18:25:00Z","avg_price":"0.01","iv_high":"0.3269","iv_low":"0.3269","premium_ask_side":9,"premium_bid_side":0,"premium_mid_side":0,"premium_no_side":0,"volume_ask_side":9,"volume_bid_side":0,"volume_mid_side":0,"volume_no_side":0,"volume_multi":9,"volume_stock_multi":0},{"close":"0.01","high":"0.01","low":"0.01","open":"0.01","start_time":"2026-05-05T17:32:00Z","avg_price":"0.01","iv_high":"0.2836","iv_low":"0.2836","premium_ask_side":110,"premium_bid_side":0,"premium_mid_side":0,"premium_no_side":0,"volume_ask_side":110,"volume_bid_side":0,"volume_mid_side":0,"volume_no_side":0,"volume_multi":110,"volume_stock_multi":0},{"close":"0.01","high":"0.01","low":"0.01","open":"0.01","start_time":"2026-05-05T17:28:00Z","avg_price":"0.01","iv_high":"0.2803","iv_low":"0.2803","premium_ask_side":1800,"premium_bid_side":0,"premium_mid_side":0,"premium_no_side":0,"volume_ask_side":1800,"volume_bid_side":0,"volume_mid_side":0,"volume_no_side":0,"volume_multi":1800,"volume_stock_multi":0},{"close":"0.01","high":"0.01","low":"0.01","open":"0.01","start_time":"2026-05-05T17:15:00Z","avg_price":"0.01","iv_high":"0.2809","iv_low":"0.2797","premium_ask_side":0,"premium_bid_side":14,"premium_mid_side":0,"premium_no_side":0,"volume_ask_side":0,"volume_bid_side":14,"volume_mid_side":0,"volume_no_side":0,"volume_multi":5,"volume_stock_multi":0},{"close":"0.01","high":"0.01","low":"0.01","open":"0.01","start_time":"2026-05-05T17:14:00Z","avg_price":"0.01","iv_high":"0.2820","iv_low":"0.2807","premium_ask_side":0,"premium_bid_side":30,"premium_mid_side":0,"premium_no_side":0,"volume_ask_side":0,"volume_bid_side":30,"volume_mid_side":0,"volume_no_side":0,"volume_multi":0,"volume_stock_multi":0},{"close":"0.01","high":"0.01","low":"0.01","open":"0.01","start_time":"2026-05-05T17:13:00Z","avg_price":"0.01","iv_high":"0.2817","iv_low":"0.2791","premium_ask_side":0,"premium_bid_side":160,"premium_mid_side":0,"premium_no_side":0,"volume_ask_side":0,"volume_bid_side":160,"volume_mid_side":0,"volume_no_side":0,"volume_multi":0,"volume_stock_multi":0},{"close":"0.01","high":"0.01","low":"0.01","open":"0.01","start_time":"2026-05-05T17:11:00Z","avg_price":"0.01","iv_high":"0.2793","iv_low":"0.2793","premium_ask_side":0,"premium_bid_side":1,"premium_mid_side":0,"premium_no_side":0,"volume_ask_side":0,"volume_bid_side":1,"volume_mid_side":0,"volume_no_side":0,"volume_multi":0,"volume_stock_multi":0},{"close":"0.01","high":"0.01","low":"0.01","open":"0.01","start_time":"2026-05-05T17:10:00Z","avg_price":"0.01","iv_high":"0.2825","iv_low":"0.2805","premium_ask_side":0,"premium_bid_side":6,"premium_mid_side":0,"premium_no_side":0,"volume_ask_side":0,"volume_bid_side":6,"volume_mid_side":0,"volume_no_side":0,"volume_multi":0,"volume_stock_multi":0},{"close":"0.01","high":"0.01","low":"0.01","open":"0.01","start_time":"2026-05-05T17:09:00Z","avg_price":"0.01","iv_high":"0.2796","iv_low":"0.2785","premium_ask_side":0,"premium_bid_side":254,"premium_mid_side":0,"premium_no_side":0,"volume_ask_side":0,"volume_bid_side":254,"volume_mid_side":0,"volume_no_side":0,"volume_multi":50,"volume_stock_multi":0},{"close":"0.01","high":"0.01","low":"0.01","open":"0.01","start_time":"2026-05-05T17:04:00Z","avg_price":"0.01","iv_high":"0.2665","iv_low":"0.2665","premium_ask_side":0,"premium_bid_side":1,"premium_mid_side":0,"premium_no_side":0,"volume_ask_side":0,"volume_bid_side":1,"volume_mid_side":0,"volume_no_side":0,"volume_multi":0,"volume_stock_multi":0},{"close":"0.01","high":"0.01","low":"0.01","open":"0.01","start_time":"2026-05-05T17:02:00Z","avg_price":"0.01","iv_high":"0.2688","iv_low":"0.2668","premium_ask_side":0,"premium_bid_side":90,"premium_mid_side":0,"premium_no_side":0,"volume_ask_side":0,"volume_bid_side":90,"volume_mid_side":0,"volume_no_side":0,"volume_multi":0,"volume_stock_multi":0},{"close":"0.01","high":"0.01","low":"0.01","open":"0.01","start_time":"2026-05-05T17:01:00Z","avg_price":"0.01","iv_high":"0.2663","iv_low":"0.2654","premium_ask_side":0,"premium_bid_side":2,"premium_mid_side":0,"premium_no_side":0,"volume_ask_side":0,"volume_bid_side":2,"volume_mid_side":0,"volume_no_side":0,"volume_multi":0,"volume_stock_multi":0},{"close":"0.01","high":"0.01","low":"0.01","open":"0.01","start_time":"2026-05-05T17:00:00Z","avg_price":"0.01","iv_high":"0.2659","iv_low":"0.2657","premium_ask_side":0,"premium_bid_side":15,"premium_mid_side":0,"premium_no_side":0,"volume_ask_side":0,"volume_bid_side":15,"volume_mid_side":0,"volume_no_side":0,"volume_multi":15,"volume_stock_multi":0},{"close":"0.01","high":"0.01","low":"0.01","open":"0.01","start_time":"2026-05-05T16:58:00Z","avg_price":"0.01","iv_high":"0.2608","iv_low":"0.2608","premium_ask_side":0,"premium_bid_side":2,"premium_mid_side":0,"premium_no_side":0,"volume_ask_side":0,"volume_bid_side":2,"volume_mid_side":0,"volume_no_side":0,"volume_multi":0,"volume_stock_multi":0},{"close":"0.01","high":"0.01","low":"0.01","open":"0.01","start_time":"2026-05-05T16:57:00Z","avg_price":"0.01","iv_high":"0.2604","iv_low":"0.2604","premium_ask_side":0,"premium_bid_side":5,"premium_mid_side":0,"premium_no_side":0,"volume_ask_side":0,"volume_bid_side":5,"volume_mid_side":0,"volume_no_side":0,"volume_multi":0,"volume_stock_multi":0},{"close":"0.01","high":"0.01","low":"0.01","open":"0.01","start_time":"2026-05-05T16:56:00Z","avg_price":"0.01","iv_high":"0.2578","iv_low":"0.2578","premium_ask_side":0,"premium_bid_side":1,"premium_mid_side":0,"premium_no_side":0,"volume_ask_side":0,"volume_bid_side":1,"volume_mid_side":0,"volume_no_side":0,"volume_multi":0,"volume_stock_multi":0},{"close":"0.01","high":"0.01","low":"0.01","open":"0.01","start_time":"2026-05-05T16:53:00Z","avg_price":"0.01","iv_high":"0.2572","iv_low":"0.2572","premium_ask_side":0,"premium_bid_side":1,"premium_mid_side":0,"premium_no_side":0,"volume_ask_side":0,"volume_bid_side":1,"volume_mid_side":0,"volume_no_side":0,"volume_multi":0,"volume_stock_multi":0},{"close":"0.01","high":"0.01","low":"0.01","open":"0.01","start_time":"2026-05-05T16:52:00Z","avg_price":"0.01","iv_high":"0.2566","iv_low":"0.2566","premium_ask_side":0,"premium_bid_side":1,"premium_mid_side":0,"premium_no_side":0,"volume_ask_side":0,"volume_bid_side":1,"volume_mid_side":0,"volume_no_side":0,"volume_multi":0,"volume_stock_multi":0},{"close":"0.01","high":"0.01","low":"0.01","open":"0.01","start_time":"2026-05-05T16:49:00Z","avg_price":"0.01","iv_high":"0.2517","iv_low":"0.2517","premium_ask_side":0,"premium_bid_side":1,"premium_mid_side":0,"premium_no_side":0,"volume_ask_side":0,"volume_bid_side":1,"volume_mid_side":0,"volume_no_side":0,"volume_multi":0,"volume_stock_multi":0},{"close":"0.01","high":"0.01","low":"0.01","open":"0.01","start_time":"2026-05-05T16:48:00Z","avg_price":"0.01","iv_high":"0.2513","iv_low":"0.2513","premium_ask_side":0,"premium_bid_side":1,"premium_mid_side":0,"premium_no_side":0,"volume_ask_side":0,"volume_bid_side":1,"volume_mid_side":0,"volume_no_side":0,"volume_multi":0,"volume_stock_multi":0},{"close":"0.01","high":"0.01","low":"0.01","open":"0.01","start_time":"2026-05-05T16:42:00Z","avg_price":"0.01","iv_high":"0.2523","iv_low":"0.2523","premium_ask_side":0,"premium_bid_side":2,"premium_mid_side":0,"premium_no_side":0,"volume_ask_side":0,"volume_bid_side":2,"volume_mid_side":0,"volume_no_side":0,"volume_multi":0,"volume_stock_multi":0},{"close":"0.01","high":"0.01","low":"0.01","open":"0.01","start_time":"2026-05-05T16:38:00Z","avg_price":"0.01","iv_high":"0.2455","iv_low":"0.2454","premium_ask_side":0,"premium_bid_side":10,"premium_mid_side":0,"premium_no_side":0,"volume_ask_side":0,"volume_bid_side":10,"volume_mid_side":0,"volume_no_side":0,"volume_multi":0,"volume_stock_multi":0},{"close":"0.01","high":"0.01","low":"0.01","open":"0.01","start_time":"2026-05-05T16:27:00Z","avg_price":"0.01","iv_high":"0.2413","iv_low":"0.2413","premium_ask_side":0,"premium_bid_side":4,"premium_mid_side":0,"premium_no_side":0,"volume_ask_side":0,"volume_bid_side":4,"volume_mid_side":0,"volume_no_side":0,"volume_multi":0,"volume_stock_multi":0},{"close":"0.01","high":"0.01","low":"0.01","open":"0.01","start_time":"2026-05-05T16:26:00Z","avg_price":"0.01","iv_high":"0.2359","iv_low":"0.2359","premium_ask_side":0,"premium_bid_side":1,"premium_mid_side":0,"premium_no_side":0,"volume_ask_side":0,"volume_bid_side":1,"volume_mid_side":0,"volume_no_side":0,"volume_multi":0,"volume_stock_multi":0},{"close":"0.01","high":"0.01","low":"0.01","open":"0.01","start_time":"2026-05-05T16:25:00Z","avg_price":"0.01","iv_high":"0.2359","iv_low":"0.2359","premium_ask_side":0,"premium_bid_side":3,"premium_mid_side":0,"premium_no_side":0,"volume_ask_side":0,"volume_bid_side":3,"volume_mid_side":0,"volume_no_side":0,"volume_multi":0,"volume_stock_multi":0},{"close":"0.01","high":"0.01","low":"0.01","open":"0.01","start_time":"2026-05-05T16:23:00Z","avg_price":"0.01","iv_high":"0.2351","iv_low":"0.2351","premium_ask_side":0,"premium_bid_side":13,"premium_mid_side":0,"premium_no_side":0,"volume_ask_side":0,"volume_bid_side":13,"volume_mid_side":0,"volume_no_side":0,"volume_multi":0,"volume_stock_multi":0},{"close":"0.01","high":"0.01","low":"0.01","open":"0.01","start_time":"2026-05-05T16:15:00Z","avg_price":"0.01","iv_high":"0.2367","iv_low":"0.2367","premium_ask_side":0,"premium_bid_side":3,"premium_mid_side":0,"premium_no_side":0,"volume_ask_side":0,"volume_bid_side":3,"volume_mid_side":0,"volume_no_side":0,"volume_multi":0,"volume_stock_multi":0},{"close":"0.01","high":"0.01","low":"0.01","open":"0.01","start_time":"2026-05-05T16:14:00Z","avg_price":"0.01","iv_high":"0.2347","iv_low":"0.2347","premium_ask_side":0,"premium_bid_side":19,"premium_mid_side":0,"premium_no_side":0,"volume_ask_side":0,"volume_bid_side":19,"volume_mid_side":0,"volume_no_side":0,"volume_multi":0,"volume_stock_multi":0},{"close":"0.01","high":"0.01","low":"0.01","open":"0.01","start_time":"2026-05-05T16:13:00Z","avg_price":"0.01","iv_high":"0.2349","iv_low":"0.2349","premium_ask_side":0,"premium_bid_side":10,"premium_mid_side":0,"premium_no_side":0,"volume_ask_side":0,"volume_bid_side":10,"volume_mid_side":0,"volume_no_side":0,"volume_multi":0,"volume_stock_multi":0},{"close":"0.01","high":"0.01","low":"0.01","open":"0.01","start_time":"2026-05-05T16:09:00Z","avg_price":"0.01","iv_high":"0.2328","iv_low":"0.2322","premium_ask_side":0,"premium_bid_side":3,"premium_mid_side":0,"premium_no_side":0,"volume_ask_side":0,"volume_bid_side":3,"volume_mid_side":0,"volume_no_side":0,"volume_multi":3,"volume_stock_multi":0},{"close":"0.01","high":"0.01","low":"0.01","open":"0.01","start_time":"2026-05-05T16:07:00Z","avg_price":"0.01","iv_high":"0.2320","iv_low":"0.2320","premium_ask_side":0,"premium_bid_side":2,"premium_mid_side":0,"premium_no_side":0,"volume_ask_side":0,"volume_bid_side":2,"volume_mid_side":0,"volume_no_side":0,"volume_multi":0,"volume_stock_multi":0},{"close":"0.01","high":"0.01","low":"0.01","open":"0.01","start_time":"2026-05-05T16:04:00Z","avg_price":"0.01","iv_high":"0.2347","iv_low":"0.2347","premium_ask_side":0,"premium_bid_side":1,"premium_mid_side":0,"premium_no_side":0,"volume_ask_side":0,"volume_bid_side":1,"volume_mid_side":0,"volume_no_side":0,"volume_multi":0,"volume_stock_multi":0},{"close":"0.01","high":"0.01","low":"0.01","open":"0.01","start_time":"2026-05-05T16:01:00Z","avg_price":"0.01","iv_high":"0.2382","iv_low":"0.2382","premium_ask_side":0,"premium_bid_side":1,"premium_mid_side":0,"premium_no_side":0,"volume_ask_side":0,"volume_bid_side":1,"volume_mid_side":0,"volume_no_side":0,"volume_multi":0,"volume_stock_multi":0},{"close":"0.01","high":"0.01","low":"0.01","open":"0.01","start_time":"2026-05-05T16:00:00Z","avg_price":"0.01","iv_high":"0.2392","iv_low":"0.2378","premium_ask_side":0,"premium_bid_side":9,"premium_mid_side":0,"premium_no_side":0,"volume_ask_side":0,"volume_bid_side":9,"volume_mid_side":0,"volume_no_side":0,"volume_multi":0,"volume_stock_multi":0},{"close":"0.01","high":"0.01","low":"0.01","open":"0.01","start_time":"2026-05-05T15:57:00Z","avg_price":"0.01","iv_high":"0.2382","iv_low":"0.2382","premium_ask_side":0,"premium_bid_side":39,"premium_mid_side":0,"premium_no_side":0,"volume_ask_side":0,"volume_bid_side":39,"volume_mid_side":0,"volume_no_side":0,"volume_multi":0,"volume_stock_multi":0},{"close":"0.01","high":"0.01","low":"0.01","open":"0.01","start_time":"2026-05-05T15:55:00Z","avg_price":"0.01","iv_high":"0.2350","iv_low":"0.2350","premium_ask_side":0,"premium_bid_side":3,"premium_mid_side":0,"premium_no_side":0,"volume_ask_side":0,"volume_bid_side":3,"volume_mid_side":0,"volume_no_side":0,"volume_multi":3,"volume_stock_multi":0},{"close":"0.01","high":"0.01","low":"0.01","open":"0.01","start_time":"2026-05-05T15:50:00Z","avg_price":"0.01","iv_high":"0.2283","iv_low":"0.2278","premium_ask_side":0,"premium_bid_side":2,"premium_mid_side":0,"premium_no_side":0,"volume_ask_side":0,"volume_bid_side":2,"volume_mid_side":0,"volume_no_side":0,"volume_multi":0,"volume_stock_multi":0},{"close":"0.01","high":"0.01","low":"0.01","open":"0.01","start_time":"2026-05-05T15:44:00Z","avg_price":"0.01","iv_high":"0.2305","iv_low":"0.2305","premium_ask_side":0,"premium_bid_side":1,"premium_mid_side":0,"premium_no_side":0,"volume_ask_side":0,"volume_bid_side":1,"volume_mid_side":0,"volume_no_side":0,"volume_multi":0,"volume_stock_multi":0},{"close":"0.01","high":"0.01","low":"0.01","open":"0.01","start_time":"2026-05-05T15:40:00Z","avg_price":"0.01","iv_high":"0.2304","iv_low":"0.2304","premium_ask_side":0,"premium_bid_side":1,"premium_mid_side":0,"premium_no_side":0,"volume_ask_side":0,"volume_bid_side":1,"volume_mid_side":0,"volume_no_side":0,"volume_multi":0,"volume_stock_multi":0},{"close":"0.02","high":"0.02","low":"0.02","open":"0.02","start_time":"2026-05-05T15:37:00Z","avg_price":"0.02","iv_high":"0.2485","iv_low":"0.2485","premium_ask_side":2,"premium_bid_side":0,"premium_mid_side":0,"premium_no_side":0,"volume_ask_side":1,"volume_bid_side":0,"volume_mid_side":0,"volume_no_side":0,"volume_multi":1,"volume_stock_multi":0},{"close":"0.01","high":"0.01","low":"0.01","open":"0.01","start_time":"2026-05-05T15:30:00Z","avg_price":"0.01","iv_high":"0.2172","iv_low":"0.2172","premium_ask_side":0,"premium_bid_side":6,"premium_mid_side":0,"premium_no_side":0,"volume_ask_side":0,"volume_bid_side":6,"volume_mid_side":0,"volume_no_side":0,"volume_multi":0,"volume_stock_multi":0},{"close":"0.01","high":"0.01","low":"0.01","open":"0.01","start_time":"2026-05-05T15:29:00Z","avg_price":"0.01","iv_high":"0.2188","iv_low":"0.2188","premium_ask_side":0,"premium_bid_side":6,"premium_mid_side":0,"premium_no_side":0,"volume_ask_side":0,"volume_bid_side":6,"volume_mid_side":0,"volume_no_side":0,"volume_multi":0,"volume_stock_multi":0},{"close":"0.01","high":"0.01","low":"0.01","open":"0.01","start_time":"2026-05-05T15:19:00Z","avg_price":"0.01","iv_high":"0.2137","iv_low":"0.2136","premium_ask_side":0,"premium_bid_side":2,"premium_mid_side":0,"premium_no_side":0,"volume_ask_side":0,"volume_bid_side":2,"volume_mid_side":0,"volume_no_side":0,"volume_multi":0,"volume_stock_multi":0},{"close":"0.01","high":"0.01","low":"0.01","open":"0.01","start_time":"2026-05-05T15:17:00Z","avg_price":"0.01","iv_high":"0.2112","iv_low":"0.2112","premium_ask_side":0,"premium_bid_side":10,"premium_mid_side":0,"premium_no_side":0,"volume_ask_side":0,"volume_bid_side":10,"volume_mid_side":0,"volume_no_side":0,"volume_multi":0,"volume_stock_multi":0},{"close":"0.02","high":"0.02","low":"0.02","open":"0.02","start_time":"2026-05-05T15:16:00Z","avg_price":"0.02","iv_high":"0.2320","iv_low":"0.2320","premium_ask_side":20,"premium_bid_side":0,"premium_mid_side":0,"premium_no_side":0,"volume_ask_side":10,"volume_bid_side":0,"volume_mid_side":0,"volume_no_side":0,"volume_multi":0,"volume_stock_multi":0},{"close":"0.01","high":"0.01","low":"0.01","open":"0.01","start_time":"2026-05-05T15:14:00Z","avg_price":"0.01","iv_high":"0.2088","iv_low":"0.2088","premium_ask_side":0,"premium_bid_side":12,"premium_mid_side":0,"premium_no_side":0,"volume_ask_side":0,"volume_bid_side":12,"volume_mid_side":0,"volume_no_side":0,"volume_multi":12,"volume_stock_multi":0},{"close":"0.01","high":"0.01","low":"0.01","open":"0.01","start_time":"2026-05-05T15:13:00Z","avg_price":"0.01","iv_high":"0.2083","iv_low":"0.2083","premium_ask_side":0,"premium_bid_side":42,"premium_mid_side":0,"premium_no_side":0,"volume_ask_side":0,"volume_bid_side":42,"volume_mid_side":0,"volume_no_side":0,"volume_multi":42,"volume_stock_multi":0},{"close":"0.02","high":"0.02","low":"0.02","open":"0.02","start_time":"2026-05-05T15:12:00Z","avg_price":"0.02","iv_high":"0.2281","iv_low":"0.2281","premium_ask_side":6,"premium_bid_side":0,"premium_mid_side":0,"premium_no_side":0,"volume_ask_side":3,"volume_bid_side":0,"volume_mid_side":0,"volume_no_side":0,"volume_multi":0,"volume_stock_multi":0},{"close":"0.01","high":"0.01","low":"0.01","open":"0.01","start_time":"2026-05-05T15:11:00Z","avg_price":"0.01","iv_high":"0.2105","iv_low":"0.2105","premium_ask_side":0,"premium_bid_side":17,"premium_mid_side":0,"premium_no_side":0,"volume_ask_side":0,"volume_bid_side":17,"volume_mid_side":0,"volume_no_side":0,"volume_multi":0,"volume_stock_multi":0},{"close":"0.01","high":"0.01","low":"0.01","open":"0.01","start_time":"2026-05-05T15:10:00Z","avg_price":"0.01","iv_high":"0.2117","iv_low":"0.2117","premium_ask_side":0,"premium_bid_side":6,"premium_mid_side":0,"premium_no_side":0,"volume_ask_side":0,"volume_bid_side":6,"volume_mid_side":0,"volume_no_side":0,"volume_multi":0,"volume_stock_multi":0},{"close":"0.01","high":"0.01","low":"0.01","open":"0.01","start_time":"2026-05-05T15:09:00Z","avg_price":"0.01","iv_high":"0.2113","iv_low":"0.2113","premium_ask_side":0,"premium_bid_side":1,"premium_mid_side":0,"premium_no_side":0,"volume_ask_side":0,"volume_bid_side":1,"volume_mid_side":0,"volume_no_side":0,"volume_multi":0,"volume_stock_multi":0},{"close":"0.01","high":"0.01","low":"0.01","open":"0.01","start_time":"2026-05-05T15:07:00Z","avg_price":"0.01","iv_high":"0.2064","iv_low":"0.2064","premium_ask_side":0,"premium_bid_side":11,"premium_mid_side":0,"premium_no_side":0,"volume_ask_side":0,"volume_bid_side":11,"volume_mid_side":0,"volume_no_side":0,"volume_multi":11,"volume_stock_multi":0},{"close":"0.01","high":"0.01","low":"0.01","open":"0.01","start_time":"2026-05-05T15:05:00Z","avg_price":"0.01","iv_high":"0.2072","iv_low":"0.2062","premium_ask_side":0,"premium_bid_side":16,"premium_mid_side":0,"premium_no_side":0,"volume_ask_side":0,"volume_bid_side":16,"volume_mid_side":0,"volume_no_side":0,"volume_multi":0,"volume_stock_multi":0},{"close":"0.01","high":"0.01","low":"0.01","open":"0.01","start_time":"2026-05-05T15:02:00Z","avg_price":"0.01","iv_high":"0.2122","iv_low":"0.2122","premium_ask_side":0,"premium_bid_side":4,"premium_mid_side":0,"premium_no_side":0,"volume_ask_side":0,"volume_bid_side":4,"volume_mid_side":0,"volume_no_side":0,"volume_multi":0,"volume_stock_multi":0},{"close":"0.02","high":"0.02","low":"0.01","open":"0.01","start_time":"2026-05-05T15:01:00Z","avg_price":"0.01","iv_high":"0.2335","iv_low":"0.2125","premium_ask_side":4,"premium_bid_side":33,"premium_mid_side":0,"premium_no_side":0,"volume_ask_side":2,"volume_bid_side":33,"volume_mid_side":0,"volume_no_side":0,"volume_multi":0,"volume_stock_multi":0},{"close":"0.01","high":"0.02","low":"0.01","open":"0.01","start_time":"2026-05-05T15:00:00Z","avg_price":"0.01","iv_high":"0.2303","iv_low":"0.2118","premium_ask_side":2,"premium_bid_side":28,"premium_mid_side":0,"premium_no_side":0,"volume_ask_side":1,"volume_bid_side":28,"volume_mid_side":0,"volume_no_side":0,"volume_multi":9,"volume_stock_multi":0},{"close":"0.02","high":"0.02","low":"0.01","open":"0.01","start_time":"2026-05-05T14:59:00Z","avg_price":"0.01","iv_high":"0.2321","iv_low":"0.2142","premium_ask_side":2,"premium_bid_side":2,"premium_mid_side":0,"premium_no_side":0,"volume_ask_side":1,"volume_bid_side":2,"volume_mid_side":0,"volume_no_side":0,"volume_multi":1,"volume_stock_multi":0},{"close":"0.01","high":"0.01","low":"0.01","open":"0.01","start_time":"2026-05-05T14:55:00Z","avg_price":"0.01","iv_high":"0.2131","iv_low":"0.2131","premium_ask_side":0,"premium_bid_side":1,"premium_mid_side":0,"premium_no_side":0,"volume_ask_side":0,"volume_bid_side":1,"volume_mid_side":0,"volume_no_side":0,"volume_multi":0,"volume_stock_multi":0},{"close":"0.01","high":"0.01","low":"0.01","open":"0.01","start_time":"2026-05-05T14:52:00Z","avg_price":"0.01","iv_high":"0.2195","iv_low":"0.2172","premium_ask_side":0,"premium_bid_side":2,"premium_mid_side":0,"premium_no_side":0,"volume_ask_side":0,"volume_bid_side":2,"volume_mid_side":0,"volume_no_side":0,"volume_multi":0,"volume_stock_multi":0},{"close":"0.01","high":"0.01","low":"0.01","open":"0.01","start_time":"2026-05-05T14:50:00Z","avg_price":"0.01","iv_high":"0.2184","iv_low":"0.2184","premium_ask_side":0,"premium_bid_side":5,"premium_mid_side":0,"premium_no_side":0,"volume_ask_side":0,"volume_bid_side":5,"volume_mid_side":0,"volume_no_side":0,"volume_multi":0,"volume_stock_multi":0},{"close":"0.01","high":"0.01","low":"0.01","open":"0.01","start_time":"2026-05-05T14:48:00Z","avg_price":"0.01","iv_high":"0.2171","iv_low":"0.2147","premium_ask_side":0,"premium_bid_side":2,"premium_mid_side":0,"premium_no_side":0,"volume_ask_side":0,"volume_bid_side":2,"volume_mid_side":0,"volume_no_side":0,"volume_multi":1,"volume_stock_multi":0},{"close":"0.01","high":"0.01","low":"0.01","open":"0.01","start_time":"2026-05-05T14:47:00Z","avg_price":"0.01","iv_high":"0.2184","iv_low":"0.2184","premium_ask_side":0,"premium_bid_side":1,"premium_mid_side":0,"premium_no_side":0,"volume_ask_side":0,"volume_bid_side":1,"volume_mid_side":0,"volume_no_side":0,"volume_multi":1,"volume_stock_multi":0},{"close":"0.01","high":"0.01","low":"0.01","open":"0.01","start_time":"2026-05-05T14:44:00Z","avg_price":"0.01","iv_high":"0.2134","iv_low":"0.2134","premium_ask_side":0,"premium_bid_side":1,"premium_mid_side":0,"premium_no_side":0,"volume_ask_side":0,"volume_bid_side":1,"volume_mid_side":0,"volume_no_side":0,"volume_multi":1,"volume_stock_multi":0},{"close":"0.01","high":"0.01","low":"0.01","open":"0.01","start_time":"2026-05-05T14:39:00Z","avg_price":"0.01","iv_high":"0.2148","iv_low":"0.2148","premium_ask_side":0,"premium_bid_side":1,"premium_mid_side":0,"premium_no_side":0,"volume_ask_side":0,"volume_bid_side":1,"volume_mid_side":0,"volume_no_side":0,"volume_multi":1,"volume_stock_multi":0},{"close":"0.01","high":"0.01","low":"0.01","open":"0.01","start_time":"2026-05-05T14:36:00Z","avg_price":"0.01","iv_high":"0.2062","iv_low":"0.2062","premium_ask_side":0,"premium_bid_side":2,"premium_mid_side":0,"premium_no_side":0,"volume_ask_side":0,"volume_bid_side":2,"volume_mid_side":0,"volume_no_side":0,"volume_multi":0,"volume_stock_multi":0},{"close":"0.01","high":"0.01","low":"0.01","open":"0.01","start_time":"2026-05-05T14:33:00Z","avg_price":"0.01","iv_high":"0.2090","iv_low":"0.2090","premium_ask_side":0,"premium_bid_side":100,"premium_mid_side":0,"premium_no_side":0,"volume_ask_side":0,"volume_bid_side":100,"volume_mid_side":0,"volume_no_side":0,"volume_multi":0,"volume_stock_multi":0},{"close":"0.02","high":"0.02","low":"0.02","open":"0.02","start_time":"2026-05-05T14:30:00Z","avg_price":"0.02","iv_high":"0.2167","iv_low":"0.2162","premium_ask_side":20,"premium_bid_side":0,"premium_mid_side":0,"premium_no_side":0,"volume_ask_side":10,"volume_bid_side":0,"volume_mid_side":0,"volume_no_side":0,"volume_multi":10,"volume_stock_multi":0},{"close":"0.01","high":"0.01","low":"0.01","open":"0.01","start_time":"2026-05-05T14:29:00Z","avg_price":"0.01","iv_high":"0.1972","iv_low":"0.1972","premium_ask_side":0,"premium_bid_side":1,"premium_mid_side":0,"premium_no_side":0,"volume_ask_side":0,"volume_bid_side":1,"volume_mid_side":0,"volume_no_side":0,"volume_multi":1,"volume_stock_multi":0},{"close":"0.01","high":"0.02","low":"0.01","open":"0.01","start_time":"2026-05-05T14:25:00Z","avg_price":"0.02","iv_high":"0.2114","iv_low":"0.1908","premium_ask_side":10,"premium_bid_side":10,"premium_mid_side":0,"premium_no_side":0,"volume_ask_side":5,"volume_bid_side":10,"volume_mid_side":0,"volume_no_side":0,"volume_multi":9,"volume_stock_multi":0},{"close":"0.02","high":"0.02","low":"0.02","open":"0.02","start_time":"2026-05-05T14:24:00Z","avg_price":"0.02","iv_high":"0.2195","iv_low":"0.2195","premium_ask_side":2,"premium_bid_side":0,"premium_mid_side":0,"premium_no_side":0,"volume_ask_side":1,"volume_bid_side":0,"volume_mid_side":0,"volume_no_side":0,"volume_multi":1,"volume_stock_multi":0},{"close":"0.01","high":"0.01","low":"0.01","open":"0.01","start_time":"2026-05-05T14:23:00Z","avg_price":"0.01","iv_high":"0.2067","iv_low":"0.2045","premium_ask_side":0,"premium_bid_side":610,"premium_mid_side":0,"premium_no_side":0,"volume_ask_side":0,"volume_bid_side":610,"volume_mid_side":0,"volume_no_side":0,"volume_multi":0,"volume_stock_multi":0},{"close":"0.01","high":"0.01","low":"0.01","open":"0.01","start_time":"2026-05-05T14:22:00Z","avg_price":"0.01","iv_high":"0.2043","iv_low":"0.2043","premium_ask_side":0,"premium_bid_side":25,"premium_mid_side":0,"premium_no_side":0,"volume_ask_side":0,"volume_bid_side":25,"volume_mid_side":0,"volume_no_side":0,"volume_multi":25,"volume_stock_multi":0},{"close":"0.01","high":"0.01","low":"0.01","open":"0.01","start_time":"2026-05-05T14:21:00Z","avg_price":"0.01","iv_high":"0.2192","iv_low":"0.2171","premium_ask_side":0,"premium_bid_side":212,"premium_mid_side":0,"premium_no_side":0,"volume_ask_side":0,"volume_bid_side":212,"volume_mid_side":0,"volume_no_side":0,"volume_multi":0,"volume_stock_multi":0},{"close":"0.01","high":"0.01","low":"0.01","open":"0.01","start_time":"2026-05-05T14:20:00Z","avg_price":"0.01","iv_high":"0.2213","iv_low":"0.2213","premium_ask_side":0,"premium_bid_side":1,"premium_mid_side":0,"premium_no_side":0,"volume_ask_side":0,"volume_bid_side":1,"volume_mid_side":0,"volume_no_side":0,"volume_multi":1,"volume_stock_multi":0},{"close":"0.01","high":"0.01","low":"0.01","open":"0.01","start_time":"2026-05-05T14:19:00Z","avg_price":"0.01","iv_high":"0.2215","iv_low":"0.2170","premium_ask_side":0,"premium_bid_side":2,"premium_mid_side":0,"premium_no_side":0,"volume_ask_side":0,"volume_bid_side":2,"volume_mid_side":0,"volume_no_side":0,"volume_multi":0,"volume_stock_multi":0},{"close":"0.01","high":"0.01","low":"0.01","open":"0.01","start_time":"2026-05-05T14:18:00Z","avg_price":"0.01","iv_high":"0.2240","iv_low":"0.2104","premium_ask_side":0,"premium_bid_side":31,"premium_mid_side":0,"premium_no_side":0,"volume_ask_side":0,"volume_bid_side":31,"volume_mid_side":0,"volume_no_side":0,"volume_multi":10,"volume_stock_multi":0},{"close":"0.02","high":"0.02","low":"0.02","open":"0.02","start_time":"2026-05-05T14:17:00Z","avg_price":"0.02","iv_high":"0.2305","iv_low":"0.2305","premium_ask_side":2,"premium_bid_side":0,"premium_mid_side":0,"premium_no_side":0,"volume_ask_side":1,"volume_bid_side":0,"volume_mid_side":0,"volume_no_side":0,"volume_multi":0,"volume_stock_multi":0},{"close":"0.02","high":"0.02","low":"0.02","open":"0.02","start_time":"2026-05-05T14:16:00Z","avg_price":"0.02","iv_high":"0.2364","iv_low":"0.2364","premium_ask_side":2,"premium_bid_side":0,"premium_mid_side":0,"premium_no_side":0,"volume_ask_side":1,"volume_bid_side":0,"volume_mid_side":0,"volume_no_side":0,"volume_multi":0,"volume_stock_multi":0},{"close":"0.01","high":"0.01","low":"0.01","open":"0.01","start_time":"2026-05-05T14:15:00Z","avg_price":"0.01","iv_high":"0.2158","iv_low":"0.2158","premium_ask_side":0,"premium_bid_side":2,"premium_mid_side":0,"premium_no_side":0,"volume_ask_side":0,"volume_bid_side":2,"volume_mid_side":0,"volume_no_side":0,"volume_multi":0,"volume_stock_multi":0},{"close":"0.02","high":"0.02","low":"0.01","open":"0.01","start_time":"2026-05-05T14:10:00Z","avg_price":"0.01","iv_high":"0.2131","iv_low":"0.1928","premium_ask_side":40,"premium_bid_side":52,"premium_mid_side":0,"premium_no_side":0,"volume_ask_side":20,"volume_bid_side":52,"volume_mid_side":0,"volume_no_side":0,"volume_multi":3,"volume_stock_multi":0},{"close":"0.02","high":"0.02","low":"0.02","open":"0.02","start_time":"2026-05-05T14:09:00Z","avg_price":"0.02","iv_high":"0.2167","iv_low":"0.2167","premium_ask_side":2,"premium_bid_side":0,"premium_mid_side":0,"premium_no_side":0,"volume_ask_side":1,"volume_bid_side":0,"volume_mid_side":0,"volume_no_side":0,"volume_multi":0,"volume_stock_multi":0},{"close":"0.02","high":"0.02","low":"0.02","open":"0.02","start_time":"2026-05-05T14:08:00Z","avg_price":"0.02","iv_high":"0.2175","iv_low":"0.2175","premium_ask_side":8,"premium_bid_side":0,"premium_mid_side":0,"premium_no_side":0,"volume_ask_side":4,"volume_bid_side":0,"volume_mid_side":0,"volume_no_side":0,"volume_multi":0,"volume_stock_multi":0},{"close":"0.02","high":"0.02","low":"0.02","open":"0.02","start_time":"2026-05-05T14:07:00Z","avg_price":"0.02","iv_high":"0.2187","iv_low":"0.2187","premium_ask_side":2,"premium_bid_side":0,"premium_mid_side":0,"premium_no_side":0,"volume_ask_side":1,"volume_bid_side":0,"volume_mid_side":0,"volume_no_side":0,"volume_multi":0,"volume_stock_multi":0},{"close":"0.01","high":"0.01","low":"0.01","open":"0.01","start_time":"2026-05-05T14:04:00Z","avg_price":"0.01","iv_high":"0.2033","iv_low":"0.2033","premium_ask_side":0,"premium_bid_side":2,"premium_mid_side":0,"premium_no_side":0,"volume_ask_side":0,"volume_bid_side":2,"volume_mid_side":0,"volume_no_side":0,"volume_multi":0,"volume_stock_multi":0},{"close":"0.02","high":"0.02","low":"0.02","open":"0.02","start_time":"2026-05-05T14:02:00Z","avg_price":"0.02","iv_high":"0.2200","iv_low":"0.2200","premium_ask_side":2,"premium_bid_side":0,"premium_mid_side":0,"premium_no_side":0,"volume_ask_side":1,"volume_bid_side":0,"volume_mid_side":0,"volume_no_side":0,"volume_multi":1,"volume_stock_multi":0},{"close":"0.01","high":"0.01","low":"0.01","open":"0.01","start_time":"2026-05-05T14:00:00Z","avg_price":"0.01","iv_high":"0.2092","iv_low":"0.2092","premium_ask_side":4,"premium_bid_side":0,"premium_mid_side":0,"premium_no_side":0,"volume_ask_side":4,"volume_bid_side":0,"volume_mid_side":0,"volume_no_side":0,"volume_multi":4,"volume_stock_multi":0},{"close":"0.02","high":"0.02","low":"0.01","open":"0.01","start_time":"2026-05-05T13:59:00Z","avg_price":"0.01","iv_high":"0.2256","iv_low":"0.2072","premium_ask_side":6,"premium_bid_side":20,"premium_mid_side":0,"premium_no_side":0,"volume_ask_side":3,"volume_bid_side":20,"volume_mid_side":0,"volume_no_side":0,"volume_multi":3,"volume_stock_multi":0},{"close":"0.02","high":"0.02","low":"0.02","open":"0.02","start_time":"2026-05-05T13:51:00Z","avg_price":"0.02","iv_high":"0.2175","iv_low":"0.2175","premium_ask_side":100,"premium_bid_side":0,"premium_mid_side":0,"premium_no_side":0,"volume_ask_side":50,"volume_bid_side":0,"volume_mid_side":0,"volume_no_side":0,"volume_multi":50,"volume_stock_multi":0},{"close":"0.01","high":"0.02","low":"0.01","open":"0.02","start_time":"2026-05-05T13:50:00Z","avg_price":"0.02","iv_high":"0.2210","iv_low":"0.2000","premium_ask_side":100,"premium_bid_side":4,"premium_mid_side":0,"premium_no_side":0,"volume_ask_side":50,"volume_bid_side":4,"volume_mid_side":0,"volume_no_side":0,"volume_multi":50,"volume_stock_multi":0},{"close":"0.01","high":"0.01","low":"0.01","open":"0.01","start_time":"2026-05-05T13:49:00Z","avg_price":"0.01","iv_high":"0.2097","iv_low":"0.2050","premium_ask_side":45,"premium_bid_side":5,"premium_mid_side":0,"premium_no_side":0,"volume_ask_side":45,"volume_bid_side":5,"volume_mid_side":0,"volume_no_side":0,"volume_multi":5,"volume_stock_multi":0},{"close":"0.01","high":"0.03","low":"0.01","open":"0.01","start_time":"2026-05-05T13:48:00Z","avg_price":"0.01","iv_high":"0.2361","iv_low":"0.2033","premium_ask_side":107,"premium_bid_side":0,"premium_mid_side":0,"premium_no_side":0,"volume_ask_side":94,"volume_bid_side":0,"volume_mid_side":0,"volume_no_side":0,"volume_multi":9,"volume_stock_multi":0},{"close":"0.01","high":"0.01","low":"0.01","open":"0.01","start_time":"2026-05-05T13:47:00Z","avg_price":"0.01","iv_high":"0.2018","iv_low":"0.2009","premium_ask_side":89,"premium_bid_side":0,"premium_mid_side":0,"premium_no_side":0,"volume_ask_side":89,"volume_bid_side":0,"volume_mid_side":0,"volume_no_side":0,"volume_multi":62,"volume_stock_multi":0},{"close":"0.01","high":"0.01","low":"0.01","open":"0.01","start_time":"2026-05-05T13:46:00Z","avg_price":"0.01","iv_high":"0.2022","iv_low":"0.2022","premium_ask_side":30,"premium_bid_side":0,"premium_mid_side":0,"premium_no_side":0,"volume_ask_side":30,"volume_bid_side":0,"volume_mid_side":0,"volume_no_side":0,"volume_multi":0,"volume_stock_multi":0},{"close":"0.01","high":"0.02","low":"0.01","open":"0.01","start_time":"2026-05-05T13:45:00Z","avg_price":"0.01","iv_high":"0.2234","iv_low":"0.2022","premium_ask_side":33,"premium_bid_side":0,"premium_mid_side":0,"premium_no_side":0,"volume_ask_side":25,"volume_bid_side":0,"volume_mid_side":0,"volume_no_side":0,"volume_multi":25,"volume_stock_multi":0},{"close":"0.01","high":"0.01","low":"0.01","open":"0.01","start_time":"2026-05-05T13:44:00Z","avg_price":"0.01","iv_high":"0.2135","iv_low":"0.2116","premium_ask_side":13,"premium_bid_side":0,"premium_mid_side":0,"premium_no_side":0,"volume_ask_side":13,"volume_bid_side":0,"volume_mid_side":0,"volume_no_side":0,"volume_multi":13,"volume_stock_multi":0},{"close":"0.01","high":"0.01","low":"0.01","open":"0.01","start_time":"2026-05-05T13:43:00Z","avg_price":"0.01","iv_high":"0.2146","iv_low":"0.2146","premium_ask_side":1,"premium_bid_side":0,"premium_mid_side":0,"premium_no_side":0,"volume_ask_side":1,"volume_bid_side":0,"volume_mid_side":0,"volume_no_side":0,"volume_multi":0,"volume_stock_multi":0},{"close":"0.01","high":"0.01","low":"0.01","open":"0.01","start_time":"2026-05-05T13:42:00Z","avg_price":"0.01","iv_high":"0.2079","iv_low":"0.2053","premium_ask_side":21,"premium_bid_side":0,"premium_mid_side":0,"premium_no_side":0,"volume_ask_side":21,"volume_bid_side":0,"volume_mid_side":0,"volume_no_side":0,"volume_multi":0,"volume_stock_multi":0},{"close":"0.01","high":"0.01","low":"0.01","open":"0.01","start_time":"2026-05-05T13:41:00Z","avg_price":"0.01","iv_high":"0.2062","iv_low":"0.2033","premium_ask_side":68,"premium_bid_side":0,"premium_mid_side":0,"premium_no_side":0,"volume_ask_side":68,"volume_bid_side":0,"volume_mid_side":0,"volume_no_side":0,"volume_multi":55,"volume_stock_multi":0},{"close":"0.01","high":"0.01","low":"0.01","open":"0.01","start_time":"2026-05-05T13:40:00Z","avg_price":"0.01","iv_high":"0.2094","iv_low":"0.2072","premium_ask_side":6,"premium_bid_side":0,"premium_mid_side":0,"premium_no_side":0,"volume_ask_side":6,"volume_bid_side":0,"volume_mid_side":0,"volume_no_side":0,"volume_multi":4,"volume_stock_multi":0},{"close":"0.01","high":"0.02","low":"0.01","open":"0.02","start_time":"2026-05-05T13:39:00Z","avg_price":"0.01","iv_high":"0.2286","iv_low":"0.2072","premium_ask_side":6,"premium_bid_side":0,"premium_mid_side":0,"premium_no_side":0,"volume_ask_side":5,"volume_bid_side":0,"volume_mid_side":0,"volume_no_side":0,"volume_multi":1,"volume_stock_multi":0},{"close":"0.01","high":"0.01","low":"0.01","open":"0.01","start_time":"2026-05-05T13:38:00Z","avg_price":"0.01","iv_high":"0.2110","iv_low":"0.2073","premium_ask_side":31,"premium_bid_side":0,"premium_mid_side":0,"premium_no_side":0,"volume_ask_side":31,"volume_bid_side":0,"volume_mid_side":0,"volume_no_side":0,"volume_multi":31,"volume_stock_multi":0},{"close":"0.01","high":"0.01","low":"0.01","open":"0.01","start_time":"2026-05-05T13:37:00Z","avg_price":"0.01","iv_high":"0.2065","iv_low":"0.2043","premium_ask_side":413,"premium_bid_side":0,"premium_mid_side":0,"premium_no_side":0,"volume_ask_side":413,"volume_bid_side":0,"volume_mid_side":0,"volume_no_side":0,"volume_multi":204,"volume_stock_multi":0},{"close":"0.01","high":"0.01","low":"0.01","open":"0.01","start_time":"2026-05-05T13:36:00Z","avg_price":"0.01","iv_high":"0.2037","iv_low":"0.2001","premium_ask_side":7,"premium_bid_side":0,"premium_mid_side":0,"premium_no_side":0,"volume_ask_side":7,"volume_bid_side":0,"volume_mid_side":0,"volume_no_side":0,"volume_multi":2,"volume_stock_multi":0},{"close":"0.01","high":"0.03","low":"0.01","open":"0.01","start_time":"2026-05-05T13:35:00Z","avg_price":"0.02","iv_high":"0.2367","iv_low":"0.2023","premium_ask_side":21,"premium_bid_side":0,"premium_mid_side":0,"premium_no_side":0,"volume_ask_side":13,"volume_bid_side":0,"volume_mid_side":0,"volume_no_side":0,"volume_multi":11,"volume_stock_multi":0},{"close":"0.01","high":"0.03","low":"0.01","open":"0.01","start_time":"2026-05-05T13:34:00Z","avg_price":"0.01","iv_high":"0.2371","iv_low":"0.2033","premium_ask_side":16,"premium_bid_side":0,"premium_mid_side":0,"premium_no_side":0,"volume_ask_side":14,"volume_bid_side":0,"volume_mid_side":0,"volume_no_side":0,"volume_multi":12,"volume_stock_multi":0},{"close":"0.01","high":"0.02","low":"0.01","open":"0.01","start_time":"2026-05-05T13:33:00Z","avg_price":"0.01","iv_high":"0.2285","iv_low":"0.2074","premium_ask_side":204,"premium_bid_side":0,"premium_mid_side":0,"premium_no_side":0,"volume_ask_side":187,"volume_bid_side":0,"volume_mid_side":0,"volume_no_side":0,"volume_multi":109,"volume_stock_multi":0},{"close":"0.01","high":"0.03","low":"0.01","open":"0.03","start_time":"2026-05-05T13:32:00Z","avg_price":"0.02","iv_high":"0.2434","iv_low":"0.2105","premium_ask_side":101,"premium_bid_side":0,"premium_mid_side":0,"premium_no_side":0,"volume_ask_side":54,"volume_bid_side":0,"volume_mid_side":0,"volume_no_side":0,"volume_multi":50,"volume_stock_multi":0},{"close":"0.01","high":"0.03","low":"0.01","open":"0.01","start_time":"2026-05-05T13:31:00Z","avg_price":"0.01","iv_high":"0.2457","iv_low":"0.2133","premium_ask_side":1813,"premium_bid_side":0,"premium_mid_side":0,"premium_no_side":0,"volume_ask_side":1809,"volume_bid_side":0,"volume_mid_side":0,"volume_no_side":0,"volume_multi":1806,"volume_stock_multi":0},{"close":"0.01","high":"0.01","low":"0.01","open":"0.01","start_time":"2026-05-05T13:30:00Z","avg_price":"0.01","iv_high":"0.2068","iv_low":"0.2064","premium_ask_side":190,"premium_bid_side":0,"premium_mid_side":0,"premium_no_side":0,"volume_ask_side":190,"volume_bid_side":0,"volume_mid_side":0,"volume_no_side":0,"volume_multi":0,"volume_stock_multi":0}]